Workbook
Name Nper: Parameters!$K$4
Name Percentages: Parameters!$K$8
Name Start_Date: Parameters!$K$6
Name Type: Parameters!$K$5
Name PV: ASTemp!$E$4
Name Decimals: Parameters!$K$7
Name PV: 'Amortization Schedule'!$E$4
Name Rate: Parameters!$K$3

Sheet Amortization Schedule
O1: =""
B2: ="Loan Payment Schedule for "&$L$4&" "&$L$5 -> Loan Payment Schedule for Mr. Eddie Kouton
B4: Loan Amount | E4: 500000 | J4: Salution | L4: Mr.
B5: Interest Rate | E5: 0.05 | F5: Yearly | J5: Borrower's Name | L5: Eddie Kouton
B6: Loan Period | E6: 12 | F6: Months | J6: Lender's Name | L6: Citi Bank
B7: Payment Frequency | E7: Weekly | J7: Date Loan Taken | L7: 42087
B8: Start Year & Month of Payment | E8: 2015 | F8: Sep | J8: Total Interest Paid | L8: =TEXT(ASTemp!L8,Decimals) -> 12844.5
B9: No. of Decimal Places in Figures | E9: 1 | J9: Total Amount Paid | L9: =TEXT(ASTemp!L9,Decimals) -> 512844.5
B10: EMI Due - Start / End of the Period
B12: Payment No. | C12: Date of Payment | D12: Year | E12: Month | F12: Starting Balance | G12: Payment | H12: Principal Payment | I12: Interest Payment | J12: Cumulative Principal | K12: Cumulative Interest | L12: Loan Remaining | M12: % of Loan Paid Up | N12: % of Loan Remaining
B13: =ASTemp!B13 -> 1 | C13: =ASTemp!C13 -> 42277 | D13: =ASTemp!D13 -> 2015 | E13: =ASTemp!E13 -> Sep | F13: =TEXT(ASTemp!F13,Decimals) -> 500000.0 | G13: =TEXT(ASTemp!G13,Decimals) -> 9862.4 | H13: =TEXT(ASTemp!H13,Decimals) -> 9381.6 | I13: =TEXT(ASTemp!I13,Decimals) -> 480.8 | J13: =TEXT(ASTemp!J13,Decimals) -> 9381.6 | K13: =TEXT(ASTemp!K13,Decimals) -> 480.8 | L13: =TEXT(ASTemp!L13,Decimals) -> 490618.4 | M13: =TEXT(ASTemp!M13,Percentages) -> 1.9% | N13: =TEXT(ASTemp!N13,Percentages) -> 98.1%
B14: =ASTemp!B14 -> 2 | C14: =ASTemp!C14 -> 42284 | D14: =ASTemp!D14 -> 2015 | E14: =ASTemp!E14 -> Oct | F14: =TEXT(ASTemp!F14,Decimals) -> 490618.4 | G14: =TEXT(ASTemp!G14,Decimals) -> 9862.4 | H14: =TEXT(ASTemp!H14,Decimals) -> 9390.6 | I14: =TEXT(ASTemp!I14,Decimals) -> 471.7 | J14: =TEXT(ASTemp!J14,Decimals) -> 18772.3 | K14: =TEXT(ASTemp!K14,Decimals) -> 952.5 | L14: =TEXT(ASTemp!L14,Decimals) -> 481227.7 | M14: =TEXT(ASTemp!M14,Percentages) -> 3.8% | N14: =TEXT(ASTemp!N14,Percentages) -> 96.2%
B15: =ASTemp!B15 -> 3 | C15: =ASTemp!C15 -> 42291 | D15: =ASTemp!D15 -> 2015 | E15: =ASTemp!E15 -> Oct | F15: =TEXT(ASTemp!F15,Decimals) -> 481227.7 | G15: =TEXT(ASTemp!G15,Decimals) -> 9862.4 | H15: =TEXT(ASTemp!H15,Decimals) -> 9399.7 | I15: =TEXT(ASTemp!I15,Decimals) -> 462.7 | J15: =TEXT(ASTemp!J15,Decimals) -> 28171.9 | K15: =TEXT(ASTemp!K15,Decimals) -> 1415.2 | L15: =TEXT(ASTemp!L15,Decimals) -> 471828.1 | M15: =TEXT(ASTemp!M15,Percentages) -> 5.6% | N15: =TEXT(ASTemp!N15,Percentages) -> 94.4%
B16: =ASTemp!B16 -> 4 | C16: =ASTemp!C16 -> 42298 | D16: =ASTemp!D16 -> 2015 | E16: =ASTemp!E16 -> Oct | F16: =TEXT(ASTemp!F16,Decimals) -> 471828.1 | G16: =TEXT(ASTemp!G16,Decimals) -> 9862.4 | H16: =TEXT(ASTemp!H16,Decimals) -> 9408.7 | I16: =TEXT(ASTemp!I16,Decimals) -> 453.7 | J16: =TEXT(ASTemp!J16,Decimals) -> 37580.7 | K16: =TEXT(ASTemp!K16,Decimals) -> 1868.9 | L16: =TEXT(ASTemp!L16,Decimals) -> 462419.3 | M16: =TEXT(ASTemp!M16,Percentages) -> 7.5% | N16: =TEXT(ASTemp!N16,Percentages) -> 92.5%
B17: =ASTemp!B17 -> 5 | C17: =ASTemp!C17 -> 42305 | D17: =ASTemp!D17 -> 2015 | E17: =ASTemp!E17 -> Oct | F17: =TEXT(ASTemp!F17,Decimals) -> 462419.3 | G17: =TEXT(ASTemp!G17,Decimals) -> 9862.4 | H17: =TEXT(ASTemp!H17,Decimals) -> 9417.8 | I17: =TEXT(ASTemp!I17,Decimals) -> 444.6 | J17: =TEXT(ASTemp!J17,Decimals) -> 46998.4 | K17: =TEXT(ASTemp!K17,Decimals) -> 2313.6 | L17: =TEXT(ASTemp!L17,Decimals) -> 453001.6 | M17: =TEXT(ASTemp!M17,Percentages) -> 9.4% | N17: =TEXT(ASTemp!N17,Percentages) -> 90.6%
B18: =ASTemp!B18 -> 6 | C18: =ASTemp!C18 -> 42312 | D18: =ASTemp!D18 -> 2015 | E18: =ASTemp!E18 -> Nov | F18: =TEXT(ASTemp!F18,Decimals) -> 453001.6 | G18: =TEXT(ASTemp!G18,Decimals) -> 9862.4 | H18: =TEXT(ASTemp!H18,Decimals) -> 9426.8 | I18: =TEXT(ASTemp!I18,Decimals) -> 435.6 | J18: =TEXT(ASTemp!J18,Decimals) -> 56425.2 | K18: =TEXT(ASTemp!K18,Decimals) -> 2749.1 | L18: =TEXT(ASTemp!L18,Decimals) -> 443574.8 | M18: =TEXT(ASTemp!M18,Percentages) -> 11.3% | N18: =TEXT(ASTemp!N18,Percentages) -> 88.7%
B19: =ASTemp!B19 -> 7 | C19: =ASTemp!C19 -> 42319 | D19: =ASTemp!D19 -> 2015 | E19: =ASTemp!E19 -> Nov | F19: =TEXT(ASTemp!F19,Decimals) -> 443574.8 | G19: =TEXT(ASTemp!G19,Decimals) -> 9862.4 | H19: =TEXT(ASTemp!H19,Decimals) -> 9435.9 | I19: =TEXT(ASTemp!I19,Decimals) -> 426.5 | J19: =TEXT(ASTemp!J19,Decimals) -> 65861.1 | K19: =TEXT(ASTemp!K19,Decimals) -> 3175.6 | L19: =TEXT(ASTemp!L19,Decimals) -> 434138.9 | M19: =TEXT(ASTemp!M19,Percentages) -> 13.2% | N19: =TEXT(ASTemp!N19,Percentages) -> 86.8%
B20: =ASTemp!B20 -> 8 | C20: =ASTemp!C20 -> 42326 | D20: =ASTemp!D20 -> 2015 | E20: =ASTemp!E20 -> Nov | F20: =TEXT(ASTemp!F20,Decimals) -> 434138.9 | G20: =TEXT(ASTemp!G20,Decimals) -> 9862.4 | H20: =TEXT(ASTemp!H20,Decimals) -> 9445.0 | I20: =TEXT(ASTemp!I20,Decimals) -> 417.4 | J20: =TEXT(ASTemp!J20,Decimals) -> 75306.1 | K20: =TEXT(ASTemp!K20,Decimals) -> 3593.1 | L20: =TEXT(ASTemp!L20,Decimals) -> 424693.9 | M20: =TEXT(ASTemp!M20,Percentages) -> 15.1% | N20: =TEXT(ASTemp!N20,Percentages) -> 84.9%
B21: =ASTemp!B21 -> 9 | C21: =ASTemp!C21 -> 42333 | D21: =ASTemp!D21 -> 2015 | E21: =ASTemp!E21 -> Nov | F21: =TEXT(ASTemp!F21,Decimals) -> 424693.9 | G21: =TEXT(ASTemp!G21,Decimals) -> 9862.4 | H21: =TEXT(ASTemp!H21,Decimals) -> 9454.0 | I21: =TEXT(ASTemp!I21,Decimals) -> 408.4 | J21: =TEXT(ASTemp!J21,Decimals) -> 84760.1 | K21: =TEXT(ASTemp!K21,Decimals) -> 4001.4 | L21: =TEXT(ASTemp!L21,Decimals) -> 415239.9 | M21: =TEXT(ASTemp!M21,Percentages) -> 17.0% | N21: =TEXT(ASTemp!N21,Percentages) -> 83.0%
B22: =ASTemp!B22 -> 10 | C22: =ASTemp!C22 -> 42340 | D22: =ASTemp!D22 -> 2015 | E22: =ASTemp!E22 -> Dec | F22: =TEXT(ASTemp!F22,Decimals) -> 415239.9 | G22: =TEXT(ASTemp!G22,Decimals) -> 9862.4 | H22: =TEXT(ASTemp!H22,Decimals) -> 9463.1 | I22: =TEXT(ASTemp!I22,Decimals) -> 399.3 | J22: =TEXT(ASTemp!J22,Decimals) -> 94223.2 | K22: =TEXT(ASTemp!K22,Decimals) -> 4400.7 | L22: =TEXT(ASTemp!L22,Decimals) -> 405776.8 | M22: =TEXT(ASTemp!M22,Percentages) -> 18.8% | N22: =TEXT(ASTemp!N22,Percentages) -> 81.2%
B23: =ASTemp!B23 -> 11 | C23: =ASTemp!C23 -> 42347 | D23: =ASTemp!D23 -> 2015 | E23: =ASTemp!E23 -> Dec | F23: =TEXT(ASTemp!F23,Decimals) -> 405776.8 | G23: =TEXT(ASTemp!G23,Decimals) -> 9862.4 | H23: =TEXT(ASTemp!H23,Decimals) -> 9472.2 | I23: =TEXT(ASTemp!I23,Decimals) -> 390.2 | J23: =TEXT(ASTemp!J23,Decimals) -> 103695.4 | K23: =TEXT(ASTemp!K23,Decimals) -> 4790.9 | L23: =TEXT(ASTemp!L23,Decimals) -> 396304.6 | M23: =TEXT(ASTemp!M23,Percentages) -> 20.7% | N23: =TEXT(ASTemp!N23,Percentages) -> 79.3%
B24: =ASTemp!B24 -> 12 | C24: =ASTemp!C24 -> 42354 | D24: =ASTemp!D24 -> 2015 | E24: =ASTemp!E24 -> Dec | F24: =TEXT(ASTemp!F24,Decimals) -> 396304.6 | G24: =TEXT(ASTemp!G24,Decimals) -> 9862.4 | H24: =TEXT(ASTemp!H24,Decimals) -> 9481.3 | I24: =TEXT(ASTemp!I24,Decimals) -> 381.1 | J24: =TEXT(ASTemp!J24,Decimals) -> 113176.8 | K24: =TEXT(ASTemp!K24,Decimals) -> 5171.9 | L24: =TEXT(ASTemp!L24,Decimals) -> 386823.2 | M24: =TEXT(ASTemp!M24,Percentages) -> 22.6% | N24: =TEXT(ASTemp!N24,Percentages) -> 77.4%
... B2611: =ASTemp!B2611 | C2611: =ASTemp!C2611 | D2611: =ASTemp!D2611 | E2611: =ASTemp!E2611 | F2611: =TEXT(ASTemp!F2611,Decimals) | G2611: =TEXT(ASTemp!G2611,Decimals) | H2611: =TEXT(ASTemp!H2611,Decimals) | I2611: =TEXT(ASTemp!I2611,Decimals) | J2611: =TEXT(ASTemp!J2611,Decimals) | K2611: =TEXT(ASTemp!K2611,Decimals) | L2611: =TEXT(ASTemp!L2611,Decimals) | M2611: =TEXT(ASTemp!M2611,Percentages) | N2611: =TEXT(ASTemp!N2611,Percentages)

Sheet ASTemp
O1: =""
B2: ="Loan Payment Schedule for "&$L$4&" "&$L$5 -> Loan Payment Schedule for Mr. Eddie Kouton
B4: Loan Amount | E4: ='Amortization Schedule'!PV -> 500000 | J4: Salution | L4: ='Amortization Schedule'!L4:N4 -> Mr.
B5: Interest Rate | E5: ='Amortization Schedule'!E5 -> 0.05 | F5: =IF('Amortization Schedule'!F5="","",'Amortization Schedule'!F5) -> Yearly | J5: Borrower's Name | L5: ='Amortization Schedule'!L5:N5 -> Eddie Kouton
B6: Loan Period | E6: ='Amortization Schedule'!E6 -> 12 | F6: =IF('Amortization Schedule'!F6="","",'Amortization Schedule'!F6) -> Months | J6: Lender's Name | L6: ='Amortization Schedule'!L6:N6 -> Citi Bank
B7: Payment Frequency | E7: =IF('Amortization Schedule'!E7="","",'Amortization Schedule'!E7) -> Weekly | J7: Date Loan Taken | L7: ='Amortization Schedule'!L7:N7 -> 42087
B8: Start Year & Month of Payment | E8: ='Amortization Schedule'!E8 -> 2015 | F8: ='Amortization Schedule'!F8 -> Sep | J8: Total Interest Paid | L8: =SUM($I$13:$I$2611) -> 12844.458
B9: No. of Decimal Places in Figures | E9: ='Amortization Schedule'!E9:F9 -> 1 | J9: Total Amount Paid | L9: =SUM($G$13:$G$2611) -> 512844.46
B10: EMI Due - Start / End of the Period
B12: Payment No. | C12: Date of Payment | D12: Year | E12: Month | F12: Starting Balance | G12: Payment | H12: Principal Payment | I12: Interest Payment | J12: Cumulative Principal | K12: Cumulative Interest | L12: Loan Remaining | M12: % of Loan Paid Up | N12: % of Loan Remaining
B13: =IF(ROWS($1:1)<=Nper,ROWS($1:1),"") -> 1 | C13: =IF($B13="","",IF($E$7="Weekly",Start_Date+7*(ROWS($1:1)-1),EDATE(Start_Date,VLOOKUP(IF(ASTemp!$E$7="","Monthly",ASTemp!$E$7),Parameters!$B$3:$D$6,3,0)*(ROWS($1:1)-1)))) -> 42277 | D13: =IF($B13="","",YEAR(C13)) -> 2015 | E13: =IF($B13="","",VLOOKUP(MONTH(C13),Parameters!$F$2:$G$13,2,0)) -> Sep | F13: =IF($B13="","",PV-N(J12)) -> 500000 | G13: =IF($B13="","",PMT(Rate,Nper,-PV,,Type)) -> 9862.3934 | H13: =IF($B13="","",PPMT(Rate,ROWS($1:1),Nper,-PV,,Type)) -> 9381.6242 | I13: =IF($B13="","",IPMT(Rate,ROWS($1:1),Nper,-PV,,Type)) -> 480.76923 | J13: =IF($B13="","",N(J12)+N(H13)) -> 9381.6242 | K13: =IF($B13="","",N(K12)+N(I13)) -> 480.76923 | L13: =IF($B13="","",PV-J13) -> 490618.38 | M13: =IF($B13="","",J13/PV) -> 0.018763248 | N13: =IF($B13="","",1-M13) -> 0.98123675
B14: =IF(ROWS($1:2)<=Nper,ROWS($1:2),"") -> 2 | C14: =IF($B14="","",IF($E$7="Weekly",Start_Date+7*(ROWS($1:2)-1),EDATE(Start_Date,VLOOKUP(IF(ASTemp!$E$7="","Monthly",ASTemp!$E$7),Parameters!$B$3:$D$6,3,0)*(ROWS($1:2)-1)))) -> 42284 | D14: =IF($B14="","",YEAR(C14)) -> 2015 | E14: =IF($B14="","",VLOOKUP(MONTH(C14),Parameters!$F$2:$G$13,2,0)) -> Oct | F14: =IF($B14="","",PV-N(J13)) -> 490618.38 | G14: =IF($B14="","",PMT(Rate,Nper,-PV,,Type)) -> 9862.3934 | H14: =IF($B14="","",PPMT(Rate,ROWS($1:2),Nper,-PV,,Type)) -> 9390.645 | I14: =IF($B14="","",IPMT(Rate,ROWS($1:2),Nper,-PV,,Type)) -> 471.74844 | J14: =IF($B14="","",N(J13)+N(H14)) -> 18772.269 | K14: =IF($B14="","",N(K13)+N(I14)) -> 952.51767 | L14: =IF($B14="","",PV-J14) -> 481227.73 | M14: =IF($B14="","",J14/PV) -> 0.037544538 | N14: =IF($B14="","",1-M14) -> 0.96245546
B15: =IF(ROWS($1:3)<=Nper,ROWS($1:3),"") -> 3 | C15: =IF($B15="","",IF($E$7="Weekly",Start_Date+7*(ROWS($1:3)-1),EDATE(Start_Date,VLOOKUP(IF(ASTemp!$E$7="","Monthly",ASTemp!$E$7),Parameters!$B$3:$D$6,3,0)*(ROWS($1:3)-1)))) -> 42291 | D15: =IF($B15="","",YEAR(C15)) -> 2015 | E15: =IF($B15="","",VLOOKUP(MONTH(C15),Parameters!$F$2:$G$13,2,0)) -> Oct | F15: =IF($B15="","",PV-N(J14)) -> 481227.73 | G15: =IF($B15="","",PMT(Rate,Nper,-PV,,Type)) -> 9862.3934 | H15: =IF($B15="","",PPMT(Rate,ROWS($1:3),Nper,-PV,,Type)) -> 9399.6745 | I15: =IF($B15="","",IPMT(Rate,ROWS($1:3),Nper,-PV,,Type)) -> 462.71897 | J15: =IF($B15="","",N(J14)+N(H15)) -> 28171.944 | K15: =IF($B15="","",N(K14)+N(I15)) -> 1415.2366 | L15: =IF($B15="","",PV-J15) -> 471828.06 | M15: =IF($B15="","",J15/PV) -> 0.056343887 | N15: =IF($B15="","",1-M15) -> 0.94365611
B16: =IF(ROWS($1:4)<=Nper,ROWS($1:4),"") -> 4 | C16: =IF($B16="","",IF($E$7="Weekly",Start_Date+7*(ROWS($1:4)-1),EDATE(Start_Date,VLOOKUP(IF(ASTemp!$E$7="","Monthly",ASTemp!$E$7),Parameters!$B$3:$D$6,3,0)*(ROWS($1:4)-1)))) -> 42298 | D16: =IF($B16="","",YEAR(C16)) -> 2015 | E16: =IF($B16="","",VLOOKUP(MONTH(C16),Parameters!$F$2:$G$13,2,0)) -> Oct | F16: =IF($B16="","",PV-N(J15)) -> 471828.06 | G16: =IF($B16="","",PMT(Rate,Nper,-PV,,Type)) -> 9862.3934 | H16: =IF($B16="","",PPMT(Rate,ROWS($1:4),Nper,-PV,,Type)) -> 9408.7126 | I16: =IF($B16="","",IPMT(Rate,ROWS($1:4),Nper,-PV,,Type)) -> 453.68082 | J16: =IF($B16="","",N(J15)+N(H16)) -> 37580.656 | K16: =IF($B16="","",N(K15)+N(I16)) -> 1868.9175 | L16: =IF($B16="","",PV-J16) -> 462419.34 | M16: =IF($B16="","",J16/PV) -> 0.075161313 | N16: =IF($B16="","",1-M16) -> 0.92483869
B17: =IF(ROWS($1:5)<=Nper,ROWS($1:5),"") -> 5 | C17: =IF($B17="","",IF($E$7="Weekly",Start_Date+7*(ROWS($1:5)-1),EDATE(Start_Date,VLOOKUP(IF(ASTemp!$E$7="","Monthly",ASTemp!$E$7),Parameters!$B$3:$D$6,3,0)*(ROWS($1:5)-1)))) -> 42305 | D17: =IF($B17="","",YEAR(C17)) -> 2015 | E17: =IF($B17="","",VLOOKUP(MONTH(C17),Parameters!$F$2:$G$13,2,0)) -> Oct | F17: =IF($B17="","",PV-N(J16)) -> 462419.34 | G17: =IF($B17="","",PMT(Rate,Nper,-PV,,Type)) -> 9862.3934 | H17: =IF($B17="","",PPMT(Rate,ROWS($1:5),Nper,-PV,,Type)) -> 9417.7594 | I17: =IF($B17="","",IPMT(Rate,ROWS($1:5),Nper,-PV,,Type)) -> 444.63398 | J17: =IF($B17="","",N(J16)+N(H17)) -> 46998.416 | K17: =IF($B17="","",N(K16)+N(I17)) -> 2313.5514 | L17: =IF($B17="","",PV-J17) -> 453001.58 | M17: =IF($B17="","",J17/PV) -> 0.093996831 | N17: =IF($B17="","",1-M17) -> 0.90600317
B18: =IF(ROWS($1:6)<=Nper,ROWS($1:6),"") -> 6 | C18: =IF($B18="","",IF($E$7="Weekly",Start_Date+7*(ROWS($1:6)-1),EDATE(Start_Date,VLOOKUP(IF(ASTemp!$E$7="","Monthly",ASTemp!$E$7),Parameters!$B$3:$D$6,3,0)*(ROWS($1:6)-1)))) -> 42312 | D18: =IF($B18="","",YEAR(C18)) -> 2015 | E18: =IF($B18="","",VLOOKUP(MONTH(C18),Parameters!$F$2:$G$13,2,0)) -> Nov | F18: =IF($B18="","",PV-N(J17)) -> 453001.58 | G18: =IF($B18="","",PMT(Rate,Nper,-PV,,Type)) -> 9862.3934 | H18: =IF($B18="","",PPMT(Rate,ROWS($1:6),Nper,-PV,,Type)) -> 9426.815 | I18: =IF($B18="","",IPMT(Rate,ROWS($1:6),Nper,-PV,,Type)) -> 435.57845 | J18: =IF($B18="","",N(J17)+N(H18)) -> 56425.231 | K18: =IF($B18="","",N(K17)+N(I18)) -> 2749.1299 | L18: =IF($B18="","",PV-J18) -> 443574.77 | M18: =IF($B18="","",J18/PV) -> 0.11285046 | N18: =IF($B18="","",1-M18) -> 0.88714954
B19: =IF(ROWS($1:7)<=Nper,ROWS($1:7),"") -> 7 | C19: =IF($B19="","",IF($E$7="Weekly",Start_Date+7*(ROWS($1:7)-1),EDATE(Start_Date,VLOOKUP(IF(ASTemp!$E$7="","Monthly",ASTemp!$E$7),Parameters!$B$3:$D$6,3,0)*(ROWS($1:7)-1)))) -> 42319 | D19: =IF($B19="","",YEAR(C19)) -> 2015 | E19: =IF($B19="","",VLOOKUP(MONTH(C19),Parameters!$F$2:$G$13,2,0)) -> Nov | F19: =IF($B19="","",PV-N(J18)) -> 443574.77 | G19: =IF($B19="","",PMT(Rate,Nper,-PV,,Type)) -> 9862.3934 | H19: =IF($B19="","",PPMT(Rate,ROWS($1:7),Nper,-PV,,Type)) -> 9435.8792 | I19: =IF($B19="","",IPMT(Rate,ROWS($1:7),Nper,-PV,,Type)) -> 426.5142 | J19: =IF($B19="","",N(J18)+N(H19)) -> 65861.11 | K19: =IF($B19="","",N(K18)+N(I19)) -> 3175.6441 | L19: =IF($B19="","",PV-J19) -> 434138.89 | M19: =IF($B19="","",J19/PV) -> 0.13172222 | N19: =IF($B19="","",1-M19) -> 0.86827778
B20: =IF(ROWS($1:8)<=Nper,ROWS($1:8),"") -> 8 | C20: =IF($B20="","",IF($E$7="Weekly",Start_Date+7*(ROWS($1:8)-1),EDATE(Start_Date,VLOOKUP(IF(ASTemp!$E$7="","Monthly",ASTemp!$E$7),Parameters!$B$3:$D$6,3,0)*(ROWS($1:8)-1)))) -> 42326 | D20: =IF($B20="","",YEAR(C20)) -> 2015 | E20: =IF($B20="","",VLOOKUP(MONTH(C20),Parameters!$F$2:$G$13,2,0)) -> Nov | F20: =IF($B20="","",PV-N(J19)) -> 434138.89 | G20: =IF($B20="","",PMT(Rate,Nper,-PV,,Type)) -> 9862.3934 | H20: =IF($B20="","",PPMT(Rate,ROWS($1:8),Nper,-PV,,Type)) -> 9444.9522 | I20: =IF($B20="","",IPMT(Rate,ROWS($1:8),Nper,-PV,,Type)) -> 417.44124 | J20: =IF($B20="","",N(J19)+N(H20)) -> 75306.062 | K20: =IF($B20="","",N(K19)+N(I20)) -> 3593.0853 | L20: =IF($B20="","",PV-J20) -> 424693.94 | M20: =IF($B20="","",J20/PV) -> 0.15061212 | N20: =IF($B20="","",1-M20) -> 0.84938788
B21: =IF(ROWS($1:9)<=Nper,ROWS($1:9),"") -> 9 | C21: =IF($B21="","",IF($E$7="Weekly",Start_Date+7*(ROWS($1:9)-1),EDATE(Start_Date,VLOOKUP(IF(ASTemp!$E$7="","Monthly",ASTemp!$E$7),Parameters!$B$3:$D$6,3,0)*(ROWS($1:9)-1)))) -> 42333 | D21: =IF($B21="","",YEAR(C21)) -> 2015 | E21: =IF($B21="","",VLOOKUP(MONTH(C21),Parameters!$F$2:$G$13,2,0)) -> Nov | F21: =IF($B21="","",PV-N(J20)) -> 424693.94 | G21: =IF($B21="","",PMT(Rate,Nper,-PV,,Type)) -> 9862.3934 | H21: =IF($B21="","",PPMT(Rate,ROWS($1:9),Nper,-PV,,Type)) -> 9454.0339 | I21: =IF($B21="","",IPMT(Rate,ROWS($1:9),Nper,-PV,,Type)) -> 408.35956 | J21: =IF($B21="","",N(J20)+N(H21)) -> 84760.096 | K21: =IF($B21="","",N(K20)+N(I21)) -> 4001.4449 | L21: =IF($B21="","",PV-J21) -> 415239.9 | M21: =IF($B21="","",J21/PV) -> 0.16952019 | N21: =IF($B21="","",1-M21) -> 0.83047981
B22: =IF(ROWS($1:10)<=Nper,ROWS($1:10),"") -> 10 | C22: =IF($B22="","",IF($E$7="Weekly",Start_Date+7*(ROWS($1:10)-1),EDATE(Start_Date,VLOOKUP(IF(ASTemp!$E$7="","Monthly",ASTemp!$E$7),Parameters!$B$3:$D$6,3,0)*(ROWS($1:10)-1)))) -> 42340 | D22: =IF($B22="","",YEAR(C22)) -> 2015 | E22: =IF($B22="","",VLOOKUP(MONTH(C22),Parameters!$F$2:$G$13,2,0)) -> Dec | F22: =IF($B22="","",PV-N(J21)) -> 415239.9 | G22: =IF($B22="","",PMT(Rate,Nper,-PV,,Type)) -> 9862.3934 | H22: =IF($B22="","",PPMT(Rate,ROWS($1:10),Nper,-PV,,Type)) -> 9463.1243 | I22: =IF($B22="","",IPMT(Rate,ROWS($1:10),Nper,-PV,,Type)) -> 399.26914 | J22: =IF($B22="","",N(J21)+N(H22)) -> 94223.22 | K22: =IF($B22="","",N(K21)+N(I22)) -> 4400.714 | L22: =IF($B22="","",PV-J22) -> 405776.78 | M22: =IF($B22="","",J22/PV) -> 0.18844644 | N22: =IF($B22="","",1-M22) -> 0.81155356
B23: =IF(ROWS($1:11)<=Nper,ROWS($1:11),"") -> 11 | C23: =IF($B23="","",IF($E$7="Weekly",Start_Date+7*(ROWS($1:11)-1),EDATE(Start_Date,VLOOKUP(IF(ASTemp!$E$7="","Monthly",ASTemp!$E$7),Parameters!$B$3:$D$6,3,0)*(ROWS($1:11)-1)))) -> 42347 | D23: =IF($B23="","",YEAR(C23)) -> 2015 | E23: =IF($B23="","",VLOOKUP(MONTH(C23),Parameters!$F$2:$G$13,2,0)) -> Dec | F23: =IF($B23="","",PV-N(J22)) -> 405776.78 | G23: =IF($B23="","",PMT(Rate,Nper,-PV,,Type)) -> 9862.3934 | H23: =IF($B23="","",PPMT(Rate,ROWS($1:11),Nper,-PV,,Type)) -> 9472.2234 | I23: =IF($B23="","",IPMT(Rate,ROWS($1:11),Nper,-PV,,Type)) -> 390.16998 | J23: =IF($B23="","",N(J22)+N(H23)) -> 103695.44 | K23: =IF($B23="","",N(K22)+N(I23)) -> 4790.884 | L23: =IF($B23="","",PV-J23) -> 396304.56 | M23: =IF($B23="","",J23/PV) -> 0.20739089 | N23: =IF($B23="","",1-M23) -> 0.79260911
B24: =IF(ROWS($1:12)<=Nper,ROWS($1:12),"") -> 12 | C24: =IF($B24="","",IF($E$7="Weekly",Start_Date+7*(ROWS($1:12)-1),EDATE(Start_Date,VLOOKUP(IF(ASTemp!$E$7="","Monthly",ASTemp!$E$7),Parameters!$B$3:$D$6,3,0)*(ROWS($1:12)-1)))) -> 42354 | D24: =IF($B24="","",YEAR(C24)) -> 2015 | E24: =IF($B24="","",VLOOKUP(MONTH(C24),Parameters!$F$2:$G$13,2,0)) -> Dec | F24: =IF($B24="","",PV-N(J23)) -> 396304.56 | G24: =IF($B24="","",PMT(Rate,Nper,-PV,,Type)) -> 9862.3934 | H24: =IF($B24="","",PPMT(Rate,ROWS($1:12),Nper,-PV,,Type)) -> 9481.3314 | I24: =IF($B24="","",IPMT(Rate,ROWS($1:12),Nper,-PV,,Type)) -> 381.06207 | J24: =IF($B24="","",N(J23)+N(H24)) -> 113176.78 | K24: =IF($B24="","",N(K23)+N(I24)) -> 5171.9461 | L24: =IF($B24="","",PV-J24) -> 386823.22 | M24: =IF($B24="","",J24/PV) -> 0.22635355 | N24: =IF($B24="","",1-M24) -> 0.77364645
B25: =IF(ROWS($1:13)<=Nper,ROWS($1:13),"") -> 13 | C25: =IF($B25="","",IF($E$7="Weekly",Start_Date+7*(ROWS($1:13)-1),EDATE(Start_Date,VLOOKUP(IF(ASTemp!$E$7="","Monthly",ASTemp!$E$7),Parameters!$B$3:$D$6,3,0)*(ROWS($1:13)-1)))) -> 42361 | D25: =IF($B25="","",YEAR(C25)) -> 2015 | E25: =IF($B25="","",VLOOKUP(MONTH(C25),Parameters!$F$2:$G$13,2,0)) -> Dec | F25: =IF($B25="","",PV-N(J24)) -> 386823.22 | G25: =IF($B25="","",PMT(Rate,Nper,-PV,,Type)) -> 9862.3934 | H25: =IF($B25="","",PPMT(Rate,ROWS($1:13),Nper,-PV,,Type)) -> 9490.448 | I25: =IF($B25="","",IPMT(Rate,ROWS($1:13),Nper,-PV,,Type)) -> 371.94541 | J25: =IF($B25="","",N(J24)+N(H25)) -> 122667.22 | K25: =IF($B25="","",N(K24)+N(I25)) -> 5543.8915 | L25: =IF($B25="","",PV-J25) -> 377332.78 | M25: =IF($B25="","",J25/PV) -> 0.24533445 | N25: =IF($B25="","",1-M25) -> 0.75466555
B26: =IF(ROWS($1:14)<=Nper,ROWS($1:14),"") -> 14 | C26: =IF($B26="","",IF($E$7="Weekly",Start_Date+7*(ROWS($1:14)-1),EDATE(Start_Date,VLOOKUP(IF(ASTemp!$E$7="","Monthly",ASTemp!$E$7),Parameters!$B$3:$D$6,3,0)*(ROWS($1:14)-1)))) -> 42368 | D26: =IF($B26="","",YEAR(C26)) -> 2015 | E26: =IF($B26="","",VLOOKUP(MONTH(C26),Parameters!$F$2:$G$13,2,0)) -> Dec | F26: =IF($B26="","",PV-N(J25)) -> 377332.78 | G26: =IF($B26="","",PMT(Rate,Nper,-PV,,Type)) -> 9862.3934 | H26: =IF($B26="","",PPMT(Rate,ROWS($1:14),Nper,-PV,,Type)) -> 9499.5735 | I26: =IF($B26="","",IPMT(Rate,ROWS($1:14),Nper,-PV,,Type)) -> 362.81998 | J26: =IF($B26="","",N(J25)+N(H26)) -> 132166.8 | K26: =IF($B26="","",N(K25)+N(I26)) -> 5906.7115 | L26: =IF($B26="","",PV-J26) -> 367833.2 | M26: =IF($B26="","",J26/PV) -> 0.26433359 | N26: =IF($B26="","",1-M26) -> 0.73566641
B27: =IF(ROWS($1:15)<=Nper,ROWS($1:15),"") -> 15 | C27: =IF($B27="","",IF($E$7="Weekly",Start_Date+7*(ROWS($1:15)-1),EDATE(Start_Date,VLOOKUP(IF(ASTemp!$E$7="","Monthly",ASTemp!$E$7),Parameters!$B$3:$D$6,3,0)*(ROWS($1:15)-1)))) -> 42375 | D27: =IF($B27="","",YEAR(C27)) -> 2016 | E27: =IF($B27="","",VLOOKUP(MONTH(C27),Parameters!$F$2:$G$13,2,0)) -> Jan | F27: =IF($B27="","",PV-N(J26)) -> 367833.2 | G27: =IF($B27="","",PMT(Rate,Nper,-PV,,Type)) -> 9862.3934 | H27: =IF($B27="","",PPMT(Rate,ROWS($1:15),Nper,-PV,,Type)) -> 9508.7077 | I27: =IF($B27="","",IPMT(Rate,ROWS($1:15),Nper,-PV,,Type)) -> 353.68577 | J27: =IF($B27="","",N(J26)+N(H27)) -> 141675.5 | K27: =IF($B27="","",N(K26)+N(I27)) -> 6260.3972 | L27: =IF($B27="","",PV-J27) -> 358324.5 | M27: =IF($B27="","",J27/PV) -> 0.28335101 | N27: =IF($B27="","",1-M27) -> 0.71664899
B28: =IF(ROWS($1:16)<=Nper,ROWS($1:16),"") -> 16 | C28: =IF($B28="","",IF($E$7="Weekly",Start_Date+7*(ROWS($1:16)-1),EDATE(Start_Date,VLOOKUP(IF(ASTemp!$E$7="","Monthly",ASTemp!$E$7),Parameters!$B$3:$D$6,3,0)*(ROWS($1:16)-1)))) -> 42382 | D28: =IF($B28="","",YEAR(C28)) -> 2016 | E28: =IF($B28="","",VLOOKUP(MONTH(C28),Parameters!$F$2:$G$13,2,0)) -> Jan | F28: =IF($B28="","",PV-N(J27)) -> 358324.5 | G28: =IF($B28="","",PMT(Rate,Nper,-PV,,Type)) -> 9862.3934 | H28: =IF($B28="","",PPMT(Rate,ROWS($1:16),Nper,-PV,,Type)) -> 9517.8506 | I28: =IF($B28="","",IPMT(Rate,ROWS($1:16),Nper,-PV,,Type)) -> 344.54278 | J28: =IF($B28="","",N(J27)+N(H28)) -> 151193.35 | K28: =IF($B28="","",N(K27)+N(I28)) -> 6604.94 | L28: =IF($B28="","",PV-J28) -> 348806.65 | M28: =IF($B28="","",J28/PV) -> 0.30238671 | N28: =IF($B28="","",1-M28) -> 0.69761329
B29: =IF(ROWS($1:17)<=Nper,ROWS($1:17),"") -> 17 | C29: =IF($B29="","",IF($E$7="Weekly",Start_Date+7*(ROWS($1:17)-1),EDATE(Start_Date,VLOOKUP(IF(ASTemp!$E$7="","Monthly",ASTemp!$E$7),Parameters!$B$3:$D$6,3,0)*(ROWS($1:17)-1)))) -> 42389 | D29: =IF($B29="","",YEAR(C29)) -> 2016 | E29: =IF($B29="","",VLOOKUP(MONTH(C29),Parameters!$F$2:$G$13,2,0)) -> Jan | F29: =IF($B29="","",PV-N(J28)) -> 348806.65 | G29: =IF($B29="","",PMT(Rate,Nper,-PV,,Type)) -> 9862.3934 | H29: =IF($B29="","",PPMT(Rate,ROWS($1:17),Nper,-PV,,Type)) -> 9527.0024 | I29: =IF($B29="","",IPMT(Rate,ROWS($1:17),Nper,-PV,,Type)) -> 335.391 | J29: =IF($B29="","",N(J28)+N(H29)) -> 160720.36 | K29: =IF($B29="","",N(K28)+N(I29)) -> 6940.331 | L29: =IF($B29="","",PV-J29) -> 339279.64 | M29: =IF($B29="","",J29/PV) -> 0.32144071 | N29: =IF($B29="","",1-M29) -> 0.67855929
B30: =IF(ROWS($1:18)<=Nper,ROWS($1:18),"") -> 18 | C30: =IF($B30="","",IF($E$7="Weekly",Start_Date+7*(ROWS($1:18)-1),EDATE(Start_Date,VLOOKUP(IF(ASTemp!$E$7="","Monthly",ASTemp!$E$7),Parameters!$B$3:$D$6,3,0)*(ROWS($1:18)-1)))) -> 42396 | D30: =IF($B30="","",YEAR(C30)) -> 2016 | E30: =IF($B30="","",VLOOKUP(MONTH(C30),Parameters!$F$2:$G$13,2,0)) -> Jan | F30: =IF($B30="","",PV-N(J29)) -> 339279.64 | G30: =IF($B30="","",PMT(Rate,Nper,-PV,,Type)) -> 9862.3934 | H30: =IF($B30="","",PPMT(Rate,ROWS($1:18),Nper,-PV,,Type)) -> 9536.163 | I30: =IF($B30="","",IPMT(Rate,ROWS($1:18),Nper,-PV,,Type)) -> 326.23043 | J30: =IF($B30="","",N(J29)+N(H30)) -> 170256.52 | K30: =IF($B30="","",N(K29)+N(I30)) -> 7266.5615 | L30: =IF($B30="","",PV-J30) -> 329743.48 | M30: =IF($B30="","",J30/PV) -> 0.34051304 | N30: =IF($B30="","",1-M30) -> 0.65948696
B31: =IF(ROWS($1:19)<=Nper,ROWS($1:19),"") -> 19 | C31: =IF($B31="","",IF($E$7="Weekly",Start_Date+7*(ROWS($1:19)-1),EDATE(Start_Date,VLOOKUP(IF(ASTemp!$E$7="","Monthly",ASTemp!$E$7),Parameters!$B$3:$D$6,3,0)*(ROWS($1:19)-1)))) -> 42403 | D31: =IF($B31="","",YEAR(C31)) -> 2016 | E31: =IF($B31="","",VLOOKUP(MONTH(C31),Parameters!$F$2:$G$13,2,0)) -> Feb | F31: =IF($B31="","",PV-N(J30)) -> 329743.48 | G31: =IF($B31="","",PMT(Rate,Nper,-PV,,Type)) -> 9862.3934 | H31: =IF($B31="","",PPMT(Rate,ROWS($1:19),Nper,-PV,,Type)) -> 9545.3324 | I31: =IF($B31="","",IPMT(Rate,ROWS($1:19),Nper,-PV,,Type)) -> 317.06104 | J31: =IF($B31="","",N(J30)+N(H31)) -> 179801.85 | K31: =IF($B31="","",N(K30)+N(I31)) -> 7583.6225 | L31: =IF($B31="","",PV-J31) -> 320198.15 | M31: =IF($B31="","",J31/PV) -> 0.35960371 | N31: =IF($B31="","",1-M31) -> 0.64039629
B32: =IF(ROWS($1:20)<=Nper,ROWS($1:20),"") -> 20 | C32: =IF($B32="","",IF($E$7="Weekly",Start_Date+7*(ROWS($1:20)-1),EDATE(Start_Date,VLOOKUP(IF(ASTemp!$E$7="","Monthly",ASTemp!$E$7),Parameters!$B$3:$D$6,3,0)*(ROWS($1:20)-1)))) -> 42410 | D32: =IF($B32="","",YEAR(C32)) -> 2016 | E32: =IF($B32="","",VLOOKUP(MONTH(C32),Parameters!$F$2:$G$13,2,0)) -> Feb | F32: =IF($B32="","",PV-N(J31)) -> 320198.15 | G32: =IF($B32="","",PMT(Rate,Nper,-PV,,Type)) -> 9862.3934 | H32: =IF($B32="","",PPMT(Rate,ROWS($1:20),Nper,-PV,,Type)) -> 9554.5106 | I32: =IF($B32="","",IPMT(Rate,ROWS($1:20),Nper,-PV,,Type)) -> 307.88283 | J32: =IF($B32="","",N(J31)+N(H32)) -> 189356.36 | K32: =IF($B32="","",N(K31)+N(I32)) -> 7891.5053 | L32: =IF($B32="","",PV-J32) -> 310643.64 | M32: =IF($B32="","",J32/PV) -> 0.37871273 | N32: =IF($B32="","",1-M32) -> 0.62128727
B33: =IF(ROWS($1:21)<=Nper,ROWS($1:21),"") -> 21 | C33: =IF($B33="","",IF($E$7="Weekly",Start_Date+7*(ROWS($1:21)-1),EDATE(Start_Date,VLOOKUP(IF(ASTemp!$E$7="","Monthly",ASTemp!$E$7),Parameters!$B$3:$D$6,3,0)*(ROWS($1:21)-1)))) -> 42417 | D33: =IF($B33="","",YEAR(C33)) -> 2016 | E33: =IF($B33="","",VLOOKUP(MONTH(C33),Parameters!$F$2:$G$13,2,0)) -> Feb | F33: =IF($B33="","",PV-N(J32)) -> 310643.64 | G33: =IF($B33="","",PMT(Rate,Nper,-PV,,Type)) -> 9862.3934 | H33: =IF($B33="","",PPMT(Rate,ROWS($1:21),Nper,-PV,,Type)) -> 9563.6976 | I33: =IF($B33="","",IPMT(Rate,ROWS($1:21),Nper,-PV,,Type)) -> 298.6958 | J33: =IF($B33="","",N(J32)+N(H33)) -> 198920.06 | K33: =IF($B33="","",N(K32)+N(I33)) -> 8190.2011 | L33: =IF($B33="","",PV-J33) -> 301079.94 | M33: =IF($B33="","",J33/PV) -> 0.39784012 | N33: =IF($B33="","",1-M33) -> 0.60215988
B34: =IF(ROWS($1:22)<=Nper,ROWS($1:22),"") -> 22 | C34: =IF($B34="","",IF($E$7="Weekly",Start_Date+7*(ROWS($1:22)-1),EDATE(Start_Date,VLOOKUP(IF(ASTemp!$E$7="","Monthly",ASTemp!$E$7),Parameters!$B$3:$D$6,3,0)*(ROWS($1:22)-1)))) -> 42424 | D34: =IF($B34="","",YEAR(C34)) -> 2016 | E34: =IF($B34="","",VLOOKUP(MONTH(C34),Parameters!$F$2:$G$13,2,0)) -> Feb | F34: =IF($B34="","",PV-N(J33)) -> 301079.94 | G34: =IF($B34="","",PMT(Rate,Nper,-PV,,Type)) -> 9862.3934 | H34: =IF($B34="","",PPMT(Rate,ROWS($1:22),Nper,-PV,,Type)) -> 9572.8935 | I34: =IF($B34="","",IPMT(Rate,ROWS($1:22),Nper,-PV,,Type)) -> 289.49994 | J34: =IF($B34="","",N(J33)+N(H34)) -> 208492.95 | K34: =IF($B34="","",N(K33)+N(I34)) -> 8479.7011 | L34: =IF($B34="","",PV-J34) -> 291507.05 | M34: =IF($B34="","",J34/PV) -> 0.41698591 | N34: =IF($B34="","",1-M34) -> 0.58301409
B35: =IF(ROWS($1:23)<=Nper,ROWS($1:23),"") -> 23 | C35: =IF($B35="","",IF($E$7="Weekly",Start_Date+7*(ROWS($1:23)-1),EDATE(Start_Date,VLOOKUP(IF(ASTemp!$E$7="","Monthly",ASTemp!$E$7),Parameters!$B$3:$D$6,3,0)*(ROWS($1:23)-1)))) -> 42431 | D35: =IF($B35="","",YEAR(C35)) -> 2016 | E35: =IF($B35="","",VLOOKUP(MONTH(C35),Parameters!$F$2:$G$13,2,0)) -> Mar | F35: =IF($B35="","",PV-N(J34)) -> 291507.05 | G35: =IF($B35="","",PMT(Rate,Nper,-PV,,Type)) -> 9862.3934 | H35: =IF($B35="","",PPMT(Rate,ROWS($1:23),Nper,-PV,,Type)) -> 9582.0982 | I35: =IF($B35="","",IPMT(Rate,ROWS($1:23),Nper,-PV,,Type)) -> 280.29524 | J35: =IF($B35="","",N(J34)+N(H35)) -> 218075.05 | K35: =IF($B35="","",N(K34)+N(I35)) -> 8759.9963 | L35: =IF($B35="","",PV-J35) -> 281924.95 | M35: =IF($B35="","",J35/PV) -> 0.43615011 | N35: =IF($B35="","",1-M35) -> 0.56384989
B36: =IF(ROWS($1:24)<=Nper,ROWS($1:24),"") -> 24 | C36: =IF($B36="","",IF($E$7="Weekly",Start_Date+7*(ROWS($1:24)-1),EDATE(Start_Date,VLOOKUP(IF(ASTemp!$E$7="","Monthly",ASTemp!$E$7),Parameters!$B$3:$D$6,3,0)*(ROWS($1:24)-1)))) -> 42438 | D36: =IF($B36="","",YEAR(C36)) -> 2016 | E36: =IF($B36="","",VLOOKUP(MONTH(C36),Parameters!$F$2:$G$13,2,0)) -> Mar | F36: =IF($B36="","",PV-N(J35)) -> 281924.95 | G36: =IF($B36="","",PMT(Rate,Nper,-PV,,Type)) -> 9862.3934 | H36: =IF($B36="","",PPMT(Rate,ROWS($1:24),Nper,-PV,,Type)) -> 9591.3118 | I36: =IF($B36="","",IPMT(Rate,ROWS($1:24),Nper,-PV,,Type)) -> 271.08168 | J36: =IF($B36="","",N(J35)+N(H36)) -> 227666.36 | K36: =IF($B36="","",N(K35)+N(I36)) -> 9031.078 | L36: =IF($B36="","",PV-J36) -> 272333.64 | M36: =IF($B36="","",J36/PV) -> 0.45533273 | N36: =IF($B36="","",1-M36) -> 0.54466727
B37: =IF(ROWS($1:25)<=Nper,ROWS($1:25),"") -> 25 | C37: =IF($B37="","",IF($E$7="Weekly",Start_Date+7*(ROWS($1:25)-1),EDATE(Start_Date,VLOOKUP(IF(ASTemp!$E$7="","Monthly",ASTemp!$E$7),Parameters!$B$3:$D$6,3,0)*(ROWS($1:25)-1)))) -> 42445 | D37: =IF($B37="","",YEAR(C37)) -> 2016 | E37: =IF($B37="","",VLOOKUP(MONTH(C37),Parameters!$F$2:$G$13,2,0)) -> Mar | F37: =IF($B37="","",PV-N(J36)) -> 272333.64 | G37: =IF($B37="","",PMT(Rate,Nper,-PV,,Type)) -> 9862.3934 | H37: =IF($B37="","",PPMT(Rate,ROWS($1:25),Nper,-PV,,Type)) -> 9600.5342 | I37: =IF($B37="","",IPMT(Rate,ROWS($1:25),Nper,-PV,,Type)) -> 261.85927 | J37: =IF($B37="","",N(J36)+N(H37)) -> 237266.9 | K37: =IF($B37="","",N(K36)+N(I37)) -> 9292.9373 | L37: =IF($B37="","",PV-J37) -> 262733.1 | M37: =IF($B37="","",J37/PV) -> 0.4745338 | N37: =IF($B37="","",1-M37) -> 0.5254662
B38: =IF(ROWS($1:26)<=Nper,ROWS($1:26),"") -> 26 | C38: =IF($B38="","",IF($E$7="Weekly",Start_Date+7*(ROWS($1:26)-1),EDATE(Start_Date,VLOOKUP(IF(ASTemp!$E$7="","Monthly",ASTemp!$E$7),Parameters!$B$3:$D$6,3,0)*(ROWS($1:26)-1)))) -> 42452 | D38: =IF($B38="","",YEAR(C38)) -> 2016 | E38: =IF($B38="","",VLOOKUP(MONTH(C38),Parameters!$F$2:$G$13,2,0)) -> Mar | F38: =IF($B38="","",PV-N(J37)) -> 262733.1 | G38: =IF($B38="","",PMT(Rate,Nper,-PV,,Type)) -> 9862.3934 | H38: =IF($B38="","",PPMT(Rate,ROWS($1:26),Nper,-PV,,Type)) -> 9609.7654 | I38: =IF($B38="","",IPMT(Rate,ROWS($1:26),Nper,-PV,,Type)) -> 252.62798 | J38: =IF($B38="","",N(J37)+N(H38)) -> 246876.66 | K38: =IF($B38="","",N(K37)+N(I38)) -> 9545.5652 | L38: =IF($B38="","",PV-J38) -> 253123.34 | M38: =IF($B38="","",J38/PV) -> 0.49375333 | N38: =IF($B38="","",1-M38) -> 0.50624667
B39: =IF(ROWS($1:27)<=Nper,ROWS($1:27),"") -> 27 | C39: =IF($B39="","",IF($E$7="Weekly",Start_Date+7*(ROWS($1:27)-1),EDATE(Start_Date,VLOOKUP(IF(ASTemp!$E$7="","Monthly",ASTemp!$E$7),Parameters!$B$3:$D$6,3,0)*(ROWS($1:27)-1)))) -> 42459 | D39: =IF($B39="","",YEAR(C39)) -> 2016 | E39: =IF($B39="","",VLOOKUP(MONTH(C39),Parameters!$F$2:$G$13,2,0)) -> Mar | F39: =IF($B39="","",PV-N(J38)) -> 253123.34 | G39: =IF($B39="","",PMT(Rate,Nper,-PV,,Type)) -> 9862.3934 | H39: =IF($B39="","",PPMT(Rate,ROWS($1:27),Nper,-PV,,Type)) -> 9619.0056 | I39: =IF($B39="","",IPMT(Rate,ROWS($1:27),Nper,-PV,,Type)) -> 243.38782 | J39: =IF($B39="","",N(J38)+N(H39)) -> 256495.67 | K39: =IF($B39="","",N(K38)+N(I39)) -> 9788.9531 | L39: =IF($B39="","",PV-J39) -> 243504.33 | M39: =IF($B39="","",J39/PV) -> 0.51299134 | N39: =IF($B39="","",1-M39) -> 0.48700866
B40: =IF(ROWS($1:28)<=Nper,ROWS($1:28),"") -> 28 | C40: =IF($B40="","",IF($E$7="Weekly",Start_Date+7*(ROWS($1:28)-1),EDATE(Start_Date,VLOOKUP(IF(ASTemp!$E$7="","Monthly",ASTemp!$E$7),Parameters!$B$3:$D$6,3,0)*(ROWS($1:28)-1)))) -> 42466 | D40: =IF($B40="","",YEAR(C40)) -> 2016 | E40: =IF($B40="","",VLOOKUP(MONTH(C40),Parameters!$F$2:$G$13,2,0)) -> Apr | F40: =IF($B40="","",PV-N(J39)) -> 243504.33 | G40: =IF($B40="","",PMT(Rate,Nper,-PV,,Type)) -> 9862.3934 | H40: =IF($B40="","",PPMT(Rate,ROWS($1:28),Nper,-PV,,Type)) -> 9628.2547 | I40: =IF($B40="","",IPMT(Rate,ROWS($1:28),Nper,-PV,,Type)) -> 234.13878 | J40: =IF($B40="","",N(J39)+N(H40)) -> 266123.92 | K40: =IF($B40="","",N(K39)+N(I40)) -> 10023.092 | L40: =IF($B40="","",PV-J40) -> 233876.08 | M40: =IF($B40="","",J40/PV) -> 0.53224785 | N40: =IF($B40="","",1-M40) -> 0.46775215
B41: =IF(ROWS($1:29)<=Nper,ROWS($1:29),"") -> 29 | C41: =IF($B41="","",IF($E$7="Weekly",Start_Date+7*(ROWS($1:29)-1),EDATE(Start_Date,VLOOKUP(IF(ASTemp!$E$7="","Monthly",ASTemp!$E$7),Parameters!$B$3:$D$6,3,0)*(ROWS($1:29)-1)))) -> 42473 | D41: =IF($B41="","",YEAR(C41)) -> 2016 | E41: =IF($B41="","",VLOOKUP(MONTH(C41),Parameters!$F$2:$G$13,2,0)) -> Apr | F41: =IF($B41="","",PV-N(J40)) -> 233876.08 | G41: =IF($B41="","",PMT(Rate,Nper,-PV,,Type)) -> 9862.3934 | H41: =IF($B41="","",PPMT(Rate,ROWS($1:29),Nper,-PV,,Type)) -> 9637.5126 | I41: =IF($B41="","",IPMT(Rate,ROWS($1:29),Nper,-PV,,Type)) -> 224.88084 | J41: =IF($B41="","",N(J40)+N(H41)) -> 275761.44 | K41: =IF($B41="","",N(K40)+N(I41)) -> 10247.973 | L41: =IF($B41="","",PV-J41) -> 224238.56 | M41: =IF($B41="","",J41/PV) -> 0.55152287 | N41: =IF($B41="","",1-M41) -> 0.44847713
B42: =IF(ROWS($1:30)<=Nper,ROWS($1:30),"") -> 30 | C42: =IF($B42="","",IF($E$7="Weekly",Start_Date+7*(ROWS($1:30)-1),EDATE(Start_Date,VLOOKUP(IF(ASTemp!$E$7="","Monthly",ASTemp!$E$7),Parameters!$B$3:$D$6,3,0)*(ROWS($1:30)-1)))) -> 42480 | D42: =IF($B42="","",YEAR(C42)) -> 2016 | E42: =IF($B42="","",VLOOKUP(MONTH(C42),Parameters!$F$2:$G$13,2,0)) -> Apr | F42: =IF($B42="","",PV-N(J41)) -> 224238.56 | G42: =IF($B42="","",PMT(Rate,Nper,-PV,,Type)) -> 9862.3934 | H42: =IF($B42="","",PPMT(Rate,ROWS($1:30),Nper,-PV,,Type)) -> 9646.7794 | I42: =IF($B42="","",IPMT(Rate,ROWS($1:30),Nper,-PV,,Type)) -> 215.614 | J42: =IF($B42="","",N(J41)+N(H42)) -> 285408.22 | K42: =IF($B42="","",N(K41)+N(I42)) -> 10463.587 | L42: =IF($B42="","",PV-J42) -> 214591.78 | M42: =IF($B42="","",J42/PV) -> 0.57081643 | N42: =IF($B42="","",1-M42) -> 0.42918357
B43: =IF(ROWS($1:31)<=Nper,ROWS($1:31),"") -> 31 | C43: =IF($B43="","",IF($E$7="Weekly",Start_Date+7*(ROWS($1:31)-1),EDATE(Start_Date,VLOOKUP(IF(ASTemp!$E$7="","Monthly",ASTemp!$E$7),Parameters!$B$3:$D$6,3,0)*(ROWS($1:31)-1)))) -> 42487 | D43: =IF($B43="","",YEAR(C43)) -> 2016 | E43: =IF($B43="","",VLOOKUP(MONTH(C43),Parameters!$F$2:$G$13,2,0)) -> Apr | F43: =IF($B43="","",PV-N(J42)) -> 214591.78 | G43: =IF($B43="","",PMT(Rate,Nper,-PV,,Type)) -> 9862.3934 | H43: =IF($B43="","",PPMT(Rate,ROWS($1:31),Nper,-PV,,Type)) -> 9656.0552 | I43: =IF($B43="","",IPMT(Rate,ROWS($1:31),Nper,-PV,,Type)) -> 206.33825 | J43: =IF($B43="","",N(J42)+N(H43)) -> 295064.27 | K43: =IF($B43="","",N(K42)+N(I43)) -> 10669.925 | L43: =IF($B43="","",PV-J43) -> 204935.73 | M43: =IF($B43="","",J43/PV) -> 0.59012854 | N43: =IF($B43="","",1-M43) -> 0.40987146
B44: =IF(ROWS($1:32)<=Nper,ROWS($1:32),"") -> 32 | C44: =IF($B44="","",IF($E$7="Weekly",Start_Date+7*(ROWS($1:32)-1),EDATE(Start_Date,VLOOKUP(IF(ASTemp!$E$7="","Monthly",ASTemp!$E$7),Parameters!$B$3:$D$6,3,0)*(ROWS($1:32)-1)))) -> 42494 | D44: =IF($B44="","",YEAR(C44)) -> 2016 | E44: =IF($B44="","",VLOOKUP(MONTH(C44),Parameters!$F$2:$G$13,2,0)) -> May | F44: =IF($B44="","",PV-N(J43)) -> 204935.73 | G44: =IF($B44="","",PMT(Rate,Nper,-PV,,Type)) -> 9862.3934 | H44: =IF($B44="","",PPMT(Rate,ROWS($1:32),Nper,-PV,,Type)) -> 9665.3398 | I44: =IF($B44="","",IPMT(Rate,ROWS($1:32),Nper,-PV,,Type)) -> 197.05359 | J44: =IF($B44="","",N(J43)+N(H44)) -> 304729.61 | K44: =IF($B44="","",N(K43)+N(I44)) -> 10866.979 | L44: =IF($B44="","",PV-J44) -> 195270.39 | M44: =IF($B44="","",J44/PV) -> 0.60945922 | N44: =IF($B44="","",1-M44) -> 0.39054078
B45: =IF(ROWS($1:33)<=Nper,ROWS($1:33),"") -> 33 | C45: =IF($B45="","",IF($E$7="Weekly",Start_Date+7*(ROWS($1:33)-1),EDATE(Start_Date,VLOOKUP(IF(ASTemp!$E$7="","Monthly",ASTemp!$E$7),Parameters!$B$3:$D$6,3,0)*(ROWS($1:33)-1)))) -> 42501 | D45: =IF($B45="","",YEAR(C45)) -> 2016 | E45: =IF($B45="","",VLOOKUP(MONTH(C45),Parameters!$F$2:$G$13,2,0)) -> May | F45: =IF($B45="","",PV-N(J44)) -> 195270.39 | G45: =IF($B45="","",PMT(Rate,Nper,-PV,,Type)) -> 9862.3934 | H45: =IF($B45="","",PPMT(Rate,ROWS($1:33),Nper,-PV,,Type)) -> 9674.6334 | I45: =IF($B45="","",IPMT(Rate,ROWS($1:33),Nper,-PV,,Type)) -> 187.75999 | J45: =IF($B45="","",N(J44)+N(H45)) -> 314404.24 | K45: =IF($B45="","",N(K44)+N(I45)) -> 11054.739 | L45: =IF($B45="","",PV-J45) -> 185595.76 | M45: =IF($B45="","",J45/PV) -> 0.62880849 | N45: =IF($B45="","",1-M45) -> 0.37119151
B46: =IF(ROWS($1:34)<=Nper,ROWS($1:34),"") -> 34 | C46: =IF($B46="","",IF($E$7="Weekly",Start_Date+7*(ROWS($1:34)-1),EDATE(Start_Date,VLOOKUP(IF(ASTemp!$E$7="","Monthly",ASTemp!$E$7),Parameters!$B$3:$D$6,3,0)*(ROWS($1:34)-1)))) -> 42508 | D46: =IF($B46="","",YEAR(C46)) -> 2016 | E46: =IF($B46="","",VLOOKUP(MONTH(C46),Parameters!$F$2:$G$13,2,0)) -> May | F46: =IF($B46="","",PV-N(J45)) -> 185595.76 | G46: =IF($B46="","",PMT(Rate,Nper,-PV,,Type)) -> 9862.3934 | H46: =IF($B46="","",PPMT(Rate,ROWS($1:34),Nper,-PV,,Type)) -> 9683.936 | I46: =IF($B46="","",IPMT(Rate,ROWS($1:34),Nper,-PV,,Type)) -> 178.45746 | J46: =IF($B46="","",N(J45)+N(H46)) -> 324088.18 | K46: =IF($B46="","",N(K45)+N(I46)) -> 11233.196 | L46: =IF($B46="","",PV-J46) -> 175911.82 | M46: =IF($B46="","",J46/PV) -> 0.64817636 | N46: =IF($B46="","",1-M46) -> 0.35182364
B47: =IF(ROWS($1:35)<=Nper,ROWS($1:35),"") -> 35 | C47: =IF($B47="","",IF($E$7="Weekly",Start_Date+7*(ROWS($1:35)-1),EDATE(Start_Date,VLOOKUP(IF(ASTemp!$E$7="","Monthly",ASTemp!$E$7),Parameters!$B$3:$D$6,3,0)*(ROWS($1:35)-1)))) -> 42515 | D47: =IF($B47="","",YEAR(C47)) -> 2016 | E47: =IF($B47="","",VLOOKUP(MONTH(C47),Parameters!$F$2:$G$13,2,0)) -> May | F47: =IF($B47="","",PV-N(J46)) -> 175911.82 | G47: =IF($B47="","",PMT(Rate,Nper,-PV,,Type)) -> 9862.3934 | H47: =IF($B47="","",PPMT(Rate,ROWS($1:35),Nper,-PV,,Type)) -> 9693.2475 | I47: =IF($B47="","",IPMT(Rate,ROWS($1:35),Nper,-PV,,Type)) -> 169.14598 | J47: =IF($B47="","",N(J46)+N(H47)) -> 333781.43 | K47: =IF($B47="","",N(K46)+N(I47)) -> 11402.342 | L47: =IF($B47="","",PV-J47) -> 166218.57 | M47: =IF($B47="","",J47/PV) -> 0.66756286 | N47: =IF($B47="","",1-M47) -> 0.33243714
B48: =IF(ROWS($1:36)<=Nper,ROWS($1:36),"") -> 36 | C48: =IF($B48="","",IF($E$7="Weekly",Start_Date+7*(ROWS($1:36)-1),EDATE(Start_Date,VLOOKUP(IF(ASTemp!$E$7="","Monthly",ASTemp!$E$7),Parameters!$B$3:$D$6,3,0)*(ROWS($1:36)-1)))) -> 42522 | D48: =IF($B48="","",YEAR(C48)) -> 2016 | E48: =IF($B48="","",VLOOKUP(MONTH(C48),Parameters!$F$2:$G$13,2,0)) -> Jun | F48: =IF($B48="","",PV-N(J47)) -> 166218.57 | G48: =IF($B48="","",PMT(Rate,Nper,-PV,,Type)) -> 9862.3934 | H48: =IF($B48="","",PPMT(Rate,ROWS($1:36),Nper,-PV,,Type)) -> 9702.5679 | I48: =IF($B48="","",IPMT(Rate,ROWS($1:36),Nper,-PV,,Type)) -> 159.82555 | J48: =IF($B48="","",N(J47)+N(H48)) -> 343484 | K48: =IF($B48="","",N(K47)+N(I48)) -> 11562.167 | L48: =IF($B48="","",PV-J48) -> 156516 | M48: =IF($B48="","",J48/PV) -> 0.68696799 | N48: =IF($B48="","",1-M48) -> 0.31303201
B49: =IF(ROWS($1:37)<=Nper,ROWS($1:37),"") -> 37 | C49: =IF($B49="","",IF($E$7="Weekly",Start_Date+7*(ROWS($1:37)-1),EDATE(Start_Date,VLOOKUP(IF(ASTemp!$E$7="","Monthly",ASTemp!$E$7),Parameters!$B$3:$D$6,3,0)*(ROWS($1:37)-1)))) -> 42529 | D49: =IF($B49="","",YEAR(C49)) -> 2016 | E49: =IF($B49="","",VLOOKUP(MONTH(C49),Parameters!$F$2:$G$13,2,0)) -> Jun | F49: =IF($B49="","",PV-N(J48)) -> 156516 | G49: =IF($B49="","",PMT(Rate,Nper,-PV,,Type)) -> 9862.3934 | H49: =IF($B49="","",PPMT(Rate,ROWS($1:37),Nper,-PV,,Type)) -> 9711.8973 | I49: =IF($B49="","",IPMT(Rate,ROWS($1:37),Nper,-PV,,Type)) -> 150.49616 | J49: =IF($B49="","",N(J48)+N(H49)) -> 353195.89 | K49: =IF($B49="","",N(K48)+N(I49)) -> 11712.664 | L49: =IF($B49="","",PV-J49) -> 146804.11 | M49: =IF($B49="","",J49/PV) -> 0.70639179 | N49: =IF($B49="","",1-M49) -> 0.29360821
B50: =IF(ROWS($1:38)<=Nper,ROWS($1:38),"") -> 38 | C50: =IF($B50="","",IF($E$7="Weekly",Start_Date+7*(ROWS($1:38)-1),EDATE(Start_Date,VLOOKUP(IF(ASTemp!$E$7="","Monthly",ASTemp!$E$7),Parameters!$B$3:$D$6,3,0)*(ROWS($1:38)-1)))) -> 42536 | D50: =IF($B50="","",YEAR(C50)) -> 2016 | E50: =IF($B50="","",VLOOKUP(MONTH(C50),Parameters!$F$2:$G$13,2,0)) -> Jun | F50: =IF($B50="","",PV-N(J49)) -> 146804.11 | G50: =IF($B50="","",PMT(Rate,Nper,-PV,,Type)) -> 9862.3934 | H50: =IF($B50="","",PPMT(Rate,ROWS($1:38),Nper,-PV,,Type)) -> 9721.2356 | I50: =IF($B50="","",IPMT(Rate,ROWS($1:38),Nper,-PV,,Type)) -> 141.15779 | J50: =IF($B50="","",N(J49)+N(H50)) -> 362917.13 | K50: =IF($B50="","",N(K49)+N(I50)) -> 11853.821 | L50: =IF($B50="","",PV-J50) -> 137082.87 | M50: =IF($B50="","",J50/PV) -> 0.72583426 | N50: =IF($B50="","",1-M50) -> 0.27416574
B51: =IF(ROWS($1:39)<=Nper,ROWS($1:39),"") -> 39 | C51: =IF($B51="","",IF($E$7="Weekly",Start_Date+7*(ROWS($1:39)-1),EDATE(Start_Date,VLOOKUP(IF(ASTemp!$E$7="","Monthly",ASTemp!$E$7),Parameters!$B$3:$D$6,3,0)*(ROWS($1:39)-1)))) -> 42543 | D51: =IF($B51="","",YEAR(C51)) -> 2016 | E51: =IF($B51="","",VLOOKUP(MONTH(C51),Parameters!$F$2:$G$13,2,0)) -> Jun | F51: =IF($B51="","",PV-N(J50)) -> 137082.87 | G51: =IF($B51="","",PMT(Rate,Nper,-PV,,Type)) -> 9862.3934 | H51: =IF($B51="","",PPMT(Rate,ROWS($1:39),Nper,-PV,,Type)) -> 9730.583 | I51: =IF($B51="","",IPMT(Rate,ROWS($1:39),Nper,-PV,,Type)) -> 131.81045 | J51: =IF($B51="","",N(J50)+N(H51)) -> 372647.71 | K51: =IF($B51="","",N(K50)+N(I51)) -> 11985.632 | L51: =IF($B51="","",PV-J51) -> 127352.29 | M51: =IF($B51="","",J51/PV) -> 0.74529542 | N51: =IF($B51="","",1-M51) -> 0.25470458
B52: =IF(ROWS($1:40)<=Nper,ROWS($1:40),"") -> 40 | C52: =IF($B52="","",IF($E$7="Weekly",Start_Date+7*(ROWS($1:40)-1),EDATE(Start_Date,VLOOKUP(IF(ASTemp!$E$7="","Monthly",ASTemp!$E$7),Parameters!$B$3:$D$6,3,0)*(ROWS($1:40)-1)))) -> 42550 | D52: =IF($B52="","",YEAR(C52)) -> 2016 | E52: =IF($B52="","",VLOOKUP(MONTH(C52),Parameters!$F$2:$G$13,2,0)) -> Jun | F52: =IF($B52="","",PV-N(J51)) -> 127352.29 | G52: =IF($B52="","",PMT(Rate,Nper,-PV,,Type)) -> 9862.3934 | H52: =IF($B52="","",PPMT(Rate,ROWS($1:40),Nper,-PV,,Type)) -> 9739.9393 | I52: =IF($B52="","",IPMT(Rate,ROWS($1:40),Nper,-PV,,Type)) -> 122.45412 | J52: =IF($B52="","",N(J51)+N(H52)) -> 382387.65 | K52: =IF($B52="","",N(K51)+N(I52)) -> 12108.086 | L52: =IF($B52="","",PV-J52) -> 117612.35 | M52: =IF($B52="","",J52/PV) -> 0.7647753 | N52: =IF($B52="","",1-M52) -> 0.2352247
B53: =IF(ROWS($1:41)<=Nper,ROWS($1:41),"") -> 41 | C53: =IF($B53="","",IF($E$7="Weekly",Start_Date+7*(ROWS($1:41)-1),EDATE(Start_Date,VLOOKUP(IF(ASTemp!$E$7="","Monthly",ASTemp!$E$7),Parameters!$B$3:$D$6,3,0)*(ROWS($1:41)-1)))) -> 42557 | D53: =IF($B53="","",YEAR(C53)) -> 2016 | E53: =IF($B53="","",VLOOKUP(MONTH(C53),Parameters!$F$2:$G$13,2,0)) -> Jul | F53: =IF($B53="","",PV-N(J52)) -> 117612.35 | G53: =IF($B53="","",PMT(Rate,Nper,-PV,,Type)) -> 9862.3934 | H53: =IF($B53="","",PPMT(Rate,ROWS($1:41),Nper,-PV,,Type)) -> 9749.3046 | I53: =IF($B53="","",IPMT(Rate,ROWS($1:41),Nper,-PV,,Type)) -> 113.0888 | J53: =IF($B53="","",N(J52)+N(H53)) -> 392136.96 | K53: =IF($B53="","",N(K52)+N(I53)) -> 12221.175 | L53: =IF($B53="","",PV-J53) -> 107863.04 | M53: =IF($B53="","",J53/PV) -> 0.78427391 | N53: =IF($B53="","",1-M53) -> 0.21572609
B54: =IF(ROWS($1:42)<=Nper,ROWS($1:42),"") -> 42 | C54: =IF($B54="","",IF($E$7="Weekly",Start_Date+7*(ROWS($1:42)-1),EDATE(Start_Date,VLOOKUP(IF(ASTemp!$E$7="","Monthly",ASTemp!$E$7),Parameters!$B$3:$D$6,3,0)*(ROWS($1:42)-1)))) -> 42564 | D54: =IF($B54="","",YEAR(C54)) -> 2016 | E54: =IF($B54="","",VLOOKUP(MONTH(C54),Parameters!$F$2:$G$13,2,0)) -> Jul | F54: =IF($B54="","",PV-N(J53)) -> 107863.04 | G54: =IF($B54="","",PMT(Rate,Nper,-PV,,Type)) -> 9862.3934 | H54: =IF($B54="","",PPMT(Rate,ROWS($1:42),Nper,-PV,,Type)) -> 9758.679 | I54: =IF($B54="","",IPMT(Rate,ROWS($1:42),Nper,-PV,,Type)) -> 103.71447 | J54: =IF($B54="","",N(J53)+N(H54)) -> 401895.63 | K54: =IF($B54="","",N(K53)+N(I54)) -> 12324.889 | L54: =IF($B54="","",PV-J54) -> 98104.365 | M54: =IF($B54="","",J54/PV) -> 0.80379127 | N54: =IF($B54="","",1-M54) -> 0.19620873
B55: =IF(ROWS($1:43)<=Nper,ROWS($1:43),"") -> 43 | C55: =IF($B55="","",IF($E$7="Weekly",Start_Date+7*(ROWS($1:43)-1),EDATE(Start_Date,VLOOKUP(IF(ASTemp!$E$7="","Monthly",ASTemp!$E$7),Parameters!$B$3:$D$6,3,0)*(ROWS($1:43)-1)))) -> 42571 | D55: =IF($B55="","",YEAR(C55)) -> 2016 | E55: =IF($B55="","",VLOOKUP(MONTH(C55),Parameters!$F$2:$G$13,2,0)) -> Jul | F55: =IF($B55="","",PV-N(J54)) -> 98104.365 | G55: =IF($B55="","",PMT(Rate,Nper,-PV,,Type)) -> 9862.3934 | H55: =IF($B55="","",PPMT(Rate,ROWS($1:43),Nper,-PV,,Type)) -> 9768.0623 | I55: =IF($B55="","",IPMT(Rate,ROWS($1:43),Nper,-PV,,Type)) -> 94.33112 | J55: =IF($B55="","",N(J54)+N(H55)) -> 411663.7 | K55: =IF($B55="","",N(K54)+N(I55)) -> 12419.22 | L55: =IF($B55="","",PV-J55) -> 88336.303 | M55: =IF($B55="","",J55/PV) -> 0.82332739 | N55: =IF($B55="","",1-M55) -> 0.17667261
B56: =IF(ROWS($1:44)<=Nper,ROWS($1:44),"") -> 44 | C56: =IF($B56="","",IF($E$7="Weekly",Start_Date+7*(ROWS($1:44)-1),EDATE(Start_Date,VLOOKUP(IF(ASTemp!$E$7="","Monthly",ASTemp!$E$7),Parameters!$B$3:$D$6,3,0)*(ROWS($1:44)-1)))) -> 42578 | D56: =IF($B56="","",YEAR(C56)) -> 2016 | E56: =IF($B56="","",VLOOKUP(MONTH(C56),Parameters!$F$2:$G$13,2,0)) -> Jul | F56: =IF($B56="","",PV-N(J55)) -> 88336.303 | G56: =IF($B56="","",PMT(Rate,Nper,-PV,,Type)) -> 9862.3934 | H56: =IF($B56="","",PPMT(Rate,ROWS($1:44),Nper,-PV,,Type)) -> 9777.4547 | I56: =IF($B56="","",IPMT(Rate,ROWS($1:44),Nper,-PV,,Type)) -> 84.938753 | J56: =IF($B56="","",N(J55)+N(H56)) -> 421441.15 | K56: =IF($B56="","",N(K55)+N(I56)) -> 12504.159 | L56: =IF($B56="","",PV-J56) -> 78558.848 | M56: =IF($B56="","",J56/PV) -> 0.8428823 | N56: =IF($B56="","",1-M56) -> 0.1571177
B57: =IF(ROWS($1:45)<=Nper,ROWS($1:45),"") -> 45 | C57: =IF($B57="","",IF($E$7="Weekly",Start_Date+7*(ROWS($1:45)-1),EDATE(Start_Date,VLOOKUP(IF(ASTemp!$E$7="","Monthly",ASTemp!$E$7),Parameters!$B$3:$D$6,3,0)*(ROWS($1:45)-1)))) -> 42585 | D57: =IF($B57="","",YEAR(C57)) -> 2016 | E57: =IF($B57="","",VLOOKUP(MONTH(C57),Parameters!$F$2:$G$13,2,0)) -> Aug | F57: =IF($B57="","",PV-N(J56)) -> 78558.848 | G57: =IF($B57="","",PMT(Rate,Nper,-PV,,Type)) -> 9862.3934 | H57: =IF($B57="","",PPMT(Rate,ROWS($1:45),Nper,-PV,,Type)) -> 9786.8561 | I57: =IF($B57="","",IPMT(Rate,ROWS($1:45),Nper,-PV,,Type)) -> 75.537354 | J57: =IF($B57="","",N(J56)+N(H57)) -> 431228.01 | K57: =IF($B57="","",N(K56)+N(I57)) -> 12579.697 | L57: =IF($B57="","",PV-J57) -> 68771.992 | M57: =IF($B57="","",J57/PV) -> 0.86245602 | N57: =IF($B57="","",1-M57) -> 0.13754398
B58: =IF(ROWS($1:46)<=Nper,ROWS($1:46),"") -> 46 | C58: =IF($B58="","",IF($E$7="Weekly",Start_Date+7*(ROWS($1:46)-1),EDATE(Start_Date,VLOOKUP(IF(ASTemp!$E$7="","Monthly",ASTemp!$E$7),Parameters!$B$3:$D$6,3,0)*(ROWS($1:46)-1)))) -> 42592 | D58: =IF($B58="","",YEAR(C58)) -> 2016 | E58: =IF($B58="","",VLOOKUP(MONTH(C58),Parameters!$F$2:$G$13,2,0)) -> Aug | F58: =IF($B58="","",PV-N(J57)) -> 68771.992 | G58: =IF($B58="","",PMT(Rate,Nper,-PV,,Type)) -> 9862.3934 | H58: =IF($B58="","",PPMT(Rate,ROWS($1:46),Nper,-PV,,Type)) -> 9796.2665 | I58: =IF($B58="","",IPMT(Rate,ROWS($1:46),Nper,-PV,,Type)) -> 66.126916 | J58: =IF($B58="","",N(J57)+N(H58)) -> 441024.27 | K58: =IF($B58="","",N(K57)+N(I58)) -> 12645.823 | L58: =IF($B58="","",PV-J58) -> 58975.726 | M58: =IF($B58="","",J58/PV) -> 0.88204855 | N58: =IF($B58="","",1-M58) -> 0.11795145
B59: =IF(ROWS($1:47)<=Nper,ROWS($1:47),"") -> 47 | C59: =IF($B59="","",IF($E$7="Weekly",Start_Date+7*(ROWS($1:47)-1),EDATE(Start_Date,VLOOKUP(IF(ASTemp!$E$7="","Monthly",ASTemp!$E$7),Parameters!$B$3:$D$6,3,0)*(ROWS($1:47)-1)))) -> 42599 | D59: =IF($B59="","",YEAR(C59)) -> 2016 | E59: =IF($B59="","",VLOOKUP(MONTH(C59),Parameters!$F$2:$G$13,2,0)) -> Aug | F59: =IF($B59="","",PV-N(J58)) -> 58975.726 | G59: =IF($B59="","",PMT(Rate,Nper,-PV,,Type)) -> 9862.3934 | H59: =IF($B59="","",PPMT(Rate,ROWS($1:47),Nper,-PV,,Type)) -> 9805.686 | I59: =IF($B59="","",IPMT(Rate,ROWS($1:47),Nper,-PV,,Type)) -> 56.707428 | J59: =IF($B59="","",N(J58)+N(H59)) -> 450829.96 | K59: =IF($B59="","",N(K58)+N(I59)) -> 12702.531 | L59: =IF($B59="","",PV-J59) -> 49170.04 | M59: =IF($B59="","",J59/PV) -> 0.90165992 | N59: =IF($B59="","",1-M59) -> 0.098340079
B60: =IF(ROWS($1:48)<=Nper,ROWS($1:48),"") -> 48 | C60: =IF($B60="","",IF($E$7="Weekly",Start_Date+7*(ROWS($1:48)-1),EDATE(Start_Date,VLOOKUP(IF(ASTemp!$E$7="","Monthly",ASTemp!$E$7),Parameters!$B$3:$D$6,3,0)*(ROWS($1:48)-1)))) -> 42606 | D60: =IF($B60="","",YEAR(C60)) -> 2016 | E60: =IF($B60="","",VLOOKUP(MONTH(C60),Parameters!$F$2:$G$13,2,0)) -> Aug | F60: =IF($B60="","",PV-N(J59)) -> 49170.04 | G60: =IF($B60="","",PMT(Rate,Nper,-PV,,Type)) -> 9862.3934 | H60: =IF($B60="","",PPMT(Rate,ROWS($1:48),Nper,-PV,,Type)) -> 9815.1145 | I60: =IF($B60="","",IPMT(Rate,ROWS($1:48),Nper,-PV,,Type)) -> 47.278884 | J60: =IF($B60="","",N(J59)+N(H60)) -> 460645.07 | K60: =IF($B60="","",N(K59)+N(I60)) -> 12749.81 | L60: =IF($B60="","",PV-J60) -> 39354.925 | M60: =IF($B60="","",J60/PV) -> 0.92129015 | N60: =IF($B60="","",1-M60) -> 0.07870985
B61: =IF(ROWS($1:49)<=Nper,ROWS($1:49),"") -> 49 | C61: =IF($B61="","",IF($E$7="Weekly",Start_Date+7*(ROWS($1:49)-1),EDATE(Start_Date,VLOOKUP(IF(ASTemp!$E$7="","Monthly",ASTemp!$E$7),Parameters!$B$3:$D$6,3,0)*(ROWS($1:49)-1)))) -> 42613 | D61: =IF($B61="","",YEAR(C61)) -> 2016 | E61: =IF($B61="","",VLOOKUP(MONTH(C61),Parameters!$F$2:$G$13,2,0)) -> Aug | F61: =IF($B61="","",PV-N(J60)) -> 39354.925 | G61: =IF($B61="","",PMT(Rate,Nper,-PV,,Type)) -> 9862.3934 | H61: =IF($B61="","",PPMT(Rate,ROWS($1:49),Nper,-PV,,Type)) -> 9824.5522 | I61: =IF($B61="","",IPMT(Rate,ROWS($1:49),Nper,-PV,,Type)) -> 37.841274 | J61: =IF($B61="","",N(J60)+N(H61)) -> 470469.63 | K61: =IF($B61="","",N(K60)+N(I61)) -> 12787.651 | L61: =IF($B61="","",PV-J61) -> 29530.373 | M61: =IF($B61="","",J61/PV) -> 0.94093925 | N61: =IF($B61="","",1-M61) -> 0.059060746
B62: =IF(ROWS($1:50)<=Nper,ROWS($1:50),"") -> 50 | C62: =IF($B62="","",IF($E$7="Weekly",Start_Date+7*(ROWS($1:50)-1),EDATE(Start_Date,VLOOKUP(IF(ASTemp!$E$7="","Monthly",ASTemp!$E$7),Parameters!$B$3:$D$6,3,0)*(ROWS($1:50)-1)))) -> 42620 | D62: =IF($B62="","",YEAR(C62)) -> 2016 | E62: =IF($B62="","",VLOOKUP(MONTH(C62),Parameters!$F$2:$G$13,2,0)) -> Sep | F62: =IF($B62="","",PV-N(J61)) -> 29530.373 | G62: =IF($B62="","",PMT(Rate,Nper,-PV,,Type)) -> 9862.3934 | H62: =IF($B62="","",PPMT(Rate,ROWS($1:50),Nper,-PV,,Type)) -> 9833.9988 | I62: =IF($B62="","",IPMT(Rate,ROWS($1:50),Nper,-PV,,Type)) -> 28.394589 | J62: =IF($B62="","",N(J61)+N(H62)) -> 480303.63 | K62: =IF($B62="","",N(K61)+N(I62)) -> 12816.046 | L62: =IF($B62="","",PV-J62) -> 19696.374 | M62: =IF($B62="","",J62/PV) -> 0.96060725 | N62: =IF($B62="","",1-M62) -> 0.039392748
B63: =IF(ROWS($1:51)<=Nper,ROWS($1:51),"") -> 51 | C63: =IF($B63="","",IF($E$7="Weekly",Start_Date+7*(ROWS($1:51)-1),EDATE(Start_Date,VLOOKUP(IF(ASTemp!$E$7="","Monthly",ASTemp!$E$7),Parameters!$B$3:$D$6,3,0)*(ROWS($1:51)-1)))) -> 42627 | D63: =IF($B63="","",YEAR(C63)) -> 2016 | E63: =IF($B63="","",VLOOKUP(MONTH(C63),Parameters!$F$2:$G$13,2,0)) -> Sep | F63: =IF($B63="","",PV-N(J62)) -> 19696.374 | G63: =IF($B63="","",PMT(Rate,Nper,-PV,,Type)) -> 9862.3934 | H63: =IF($B63="","",PPMT(Rate,ROWS($1:51),Nper,-PV,,Type)) -> 9843.4546 | I63: =IF($B63="","",IPMT(Rate,ROWS($1:51),Nper,-PV,,Type)) -> 18.938821 | J63: =IF($B63="","",N(J62)+N(H63)) -> 490147.08 | K63: =IF($B63="","",N(K62)+N(I63)) -> 12834.984 | L63: =IF($B63="","",PV-J63) -> 9852.9195 | M63: =IF($B63="","",J63/PV) -> 0.98029416 | N63: =IF($B63="","",1-M63) -> 0.019705839
B64: =IF(ROWS($1:52)<=Nper,ROWS($1:52),"") -> 52 | C64: =IF($B64="","",IF($E$7="Weekly",Start_Date+7*(ROWS($1:52)-1),EDATE(Start_Date,VLOOKUP(IF(ASTemp!$E$7="","Monthly",ASTemp!$E$7),Parameters!$B$3:$D$6,3,0)*(ROWS($1:52)-1)))) -> 42634 | D64: =IF($B64="","",YEAR(C64)) -> 2016 | E64: =IF($B64="","",VLOOKUP(MONTH(C64),Parameters!$F$2:$G$13,2,0)) -> Sep | F64: =IF($B64="","",PV-N(J63)) -> 9852.9195 | G64: =IF($B64="","",PMT(Rate,Nper,-PV,,Type)) -> 9862.3934 | H64: =IF($B64="","",PPMT(Rate,ROWS($1:52),Nper,-PV,,Type)) -> 9852.9195 | I64: =IF($B64="","",IPMT(Rate,ROWS($1:52),Nper,-PV,,Type)) -> 9.473961 | J64: =IF($B64="","",N(J63)+N(H64)) -> 500000 | K64: =IF($B64="","",N(K63)+N(I64)) -> 12844.458 | L64: =IF($B64="","",PV-J64) -> -1.4551915e-09 | M64: =IF($B64="","",J64/PV) -> 1 | N64: =IF($B64="","",1-M64) -> 0
B65: =IF(ROWS($1:53)<=Nper,ROWS($1:53),"") | C65: =IF($B65="","",IF($E$7="Weekly",Start_Date+7*(ROWS($1:53)-1),EDATE(Start_Date,VLOOKUP(IF(ASTemp!$E$7="","Monthly",ASTemp!$E$7),Parameters!$B$3:$D$6,3,0)*(ROWS($1:53)-1)))) | D65: =IF($B65="","",YEAR(C65)) | E65: =IF($B65="","",VLOOKUP(MONTH(C65),Parameters!$F$2:$G$13,2,0)) | F65: =IF($B65="","",PV-N(J64)) | G65: =IF($B65="","",PMT(Rate,Nper,-PV,,Type)) | H65: =IF($B65="","",PPMT(Rate,ROWS($1:53),Nper,-PV,,Type)) | I65: =IF($B65="","",IPMT(Rate,ROWS($1:53),Nper,-PV,,Type)) | J65: =IF($B65="","",N(J64)+N(H65)) | K65: =IF($B65="","",N(K64)+N(I65)) | L65: =IF($B65="","",PV-J65) | M65: =IF($B65="","",J65/PV) | N65: =IF($B65="","",1-M65)
B66: =IF(ROWS($1:54)<=Nper,ROWS($1:54),"") | C66: =IF($B66="","",IF($E$7="Weekly",Start_Date+7*(ROWS($1:54)-1),EDATE(Start_Date,VLOOKUP(IF(ASTemp!$E$7="","Monthly",ASTemp!$E$7),Parameters!$B$3:$D$6,3,0)*(ROWS($1:54)-1)))) | D66: =IF($B66="","",YEAR(C66)) | E66: =IF($B66="","",VLOOKUP(MONTH(C66),Parameters!$F$2:$G$13,2,0)) | F66: =IF($B66="","",PV-N(J65)) | G66: =IF($B66="","",PMT(Rate,Nper,-PV,,Type)) | H66: =IF($B66="","",PPMT(Rate,ROWS($1:54),Nper,-PV,,Type)) | I66: =IF($B66="","",IPMT(Rate,ROWS($1:54),Nper,-PV,,Type)) | J66: =IF($B66="","",N(J65)+N(H66)) | K66: =IF($B66="","",N(K65)+N(I66)) | L66: =IF($B66="","",PV-J66) | M66: =IF($B66="","",J66/PV) | N66: =IF($B66="","",1-M66)
B67: =IF(ROWS($1:55)<=Nper,ROWS($1:55),"") | C67: =IF($B67="","",IF($E$7="Weekly",Start_Date+7*(ROWS($1:55)-1),EDATE(Start_Date,VLOOKUP(IF(ASTemp!$E$7="","Monthly",ASTemp!$E$7),Parameters!$B$3:$D$6,3,0)*(ROWS($1:55)-1)))) | D67: =IF($B67="","",YEAR(C67)) | E67: =IF($B67="","",VLOOKUP(MONTH(C67),Parameters!$F$2:$G$13,2,0)) | F67: =IF($B67="","",PV-N(J66)) | G67: =IF($B67="","",PMT(Rate,Nper,-PV,,Type)) | H67: =IF($B67="","",PPMT(Rate,ROWS($1:55),Nper,-PV,,Type)) | I67: =IF($B67="","",IPMT(Rate,ROWS($1:55),Nper,-PV,,Type)) | J67: =IF($B67="","",N(J66)+N(H67)) | K67: =IF($B67="","",N(K66)+N(I67)) | L67: =IF($B67="","",PV-J67) | M67: =IF($B67="","",J67/PV) | N67: =IF($B67="","",1-M67)
B68: =IF(ROWS($1:56)<=Nper,ROWS($1:56),"") | C68: =IF($B68="","",IF($E$7="Weekly",Start_Date+7*(ROWS($1:56)-1),EDATE(Start_Date,VLOOKUP(IF(ASTemp!$E$7="","Monthly",ASTemp!$E$7),Parameters!$B$3:$D$6,3,0)*(ROWS($1:56)-1)))) | D68: =IF($B68="","",YEAR(C68)) | E68: =IF($B68="","",VLOOKUP(MONTH(C68),Parameters!$F$2:$G$13,2,0)) | F68: =IF($B68="","",PV-N(J67)) | G68: =IF($B68="","",PMT(Rate,Nper,-PV,,Type)) | H68: =IF($B68="","",PPMT(Rate,ROWS($1:56),Nper,-PV,,Type)) | I68: =IF($B68="","",IPMT(Rate,ROWS($1:56),Nper,-PV,,Type)) | J68: =IF($B68="","",N(J67)+N(H68)) | K68: =IF($B68="","",N(K67)+N(I68)) | L68: =IF($B68="","",PV-J68) | M68: =IF($B68="","",J68/PV) | N68: =IF($B68="","",1-M68)
B69: =IF(ROWS($1:57)<=Nper,ROWS($1:57),"") | C69: =IF($B69="","",IF($E$7="Weekly",Start_Date+7*(ROWS($1:57)-1),EDATE(Start_Date,VLOOKUP(IF(ASTemp!$E$7="","Monthly",ASTemp!$E$7),Parameters!$B$3:$D$6,3,0)*(ROWS($1:57)-1)))) | D69: =IF($B69="","",YEAR(C69)) | E69: =IF($B69="","",VLOOKUP(MONTH(C69),Parameters!$F$2:$G$13,2,0)) | F69: =IF($B69="","",PV-N(J68)) | G69: =IF($B69="","",PMT(Rate,Nper,-PV,,Type)) | H69: =IF($B69="","",PPMT(Rate,ROWS($1:57),Nper,-PV,,Type)) | I69: =IF($B69="","",IPMT(Rate,ROWS($1:57),Nper,-PV,,Type)) | J69: =IF($B69="","",N(J68)+N(H69)) | K69: =IF($B69="","",N(K68)+N(I69)) | L69: =IF($B69="","",PV-J69) | M69: =IF($B69="","",J69/PV) | N69: =IF($B69="","",1-M69)
B70: =IF(ROWS($1:58)<=Nper,ROWS($1:58),"") | C70: =IF($B70="","",IF($E$7="Weekly",Start_Date+7*(ROWS($1:58)-1),EDATE(Start_Date,VLOOKUP(IF(ASTemp!$E$7="","Monthly",ASTemp!$E$7),Parameters!$B$3:$D$6,3,0)*(ROWS($1:58)-1)))) | D70: =IF($B70="","",YEAR(C70)) | E70: =IF($B70="","",VLOOKUP(MONTH(C70),Parameters!$F$2:$G$13,2,0)) | F70: =IF($B70="","",PV-N(J69)) | G70: =IF($B70="","",PMT(Rate,Nper,-PV,,Type)) | H70: =IF($B70="","",PPMT(Rate,ROWS($1:58),Nper,-PV,,Type)) | I70: =IF($B70="","",IPMT(Rate,ROWS($1:58),Nper,-PV,,Type)) | J70: =IF($B70="","",N(J69)+N(H70)) | K70: =IF($B70="","",N(K69)+N(I70)) | L70: =IF($B70="","",PV-J70) | M70: =IF($B70="","",J70/PV) | N70: =IF($B70="","",1-M70)
B71: =IF(ROWS($1:59)<=Nper,ROWS($1:59),"") | C71: =IF($B71="","",IF($E$7="Weekly",Start_Date+7*(ROWS($1:59)-1),EDATE(Start_Date,VLOOKUP(IF(ASTemp!$E$7="","Monthly",ASTemp!$E$7),Parameters!$B$3:$D$6,3,0)*(ROWS($1:59)-1)))) | D71: =IF($B71="","",YEAR(C71)) | E71: =IF($B71="","",VLOOKUP(MONTH(C71),Parameters!$F$2:$G$13,2,0)) | F71: =IF($B71="","",PV-N(J70)) | G71: =IF($B71="","",PMT(Rate,Nper,-PV,,Type)) | H71: =IF($B71="","",PPMT(Rate,ROWS($1:59),Nper,-PV,,Type)) | I71: =IF($B71="","",IPMT(Rate,ROWS($1:59),Nper,-PV,,Type)) | J71: =IF($B71="","",N(J70)+N(H71)) | K71: =IF($B71="","",N(K70)+N(I71)) | L71: =IF($B71="","",PV-J71) | M71: =IF($B71="","",J71/PV) | N71: =IF($B71="","",1-M71)
B72: =IF(ROWS($1:60)<=Nper,ROWS($1:60),"") | C72: =IF($B72="","",IF($E$7="Weekly",Start_Date+7*(ROWS($1:60)-1),EDATE(Start_Date,VLOOKUP(IF(ASTemp!$E$7="","Monthly",ASTemp!$E$7),Parameters!$B$3:$D$6,3,0)*(ROWS($1:60)-1)))) | D72: =IF($B72="","",YEAR(C72)) | E72: =IF($B72="","",VLOOKUP(MONTH(C72),Parameters!$F$2:$G$13,2,0)) | F72: =IF($B72="","",PV-N(J71)) | G72: =IF($B72="","",PMT(Rate,Nper,-PV,,Type)) | H72: =IF($B72="","",PPMT(Rate,ROWS($1:60),Nper,-PV,,Type)) | I72: =IF($B72="","",IPMT(Rate,ROWS($1:60),Nper,-PV,,Type)) | J72: =IF($B72="","",N(J71)+N(H72)) | K72: =IF($B72="","",N(K71)+N(I72)) | L72: =IF($B72="","",PV-J72) | M72: =IF($B72="","",J72/PV) | N72: =IF($B72="","",1-M72)
B73: =IF(ROWS($1:61)<=Nper,ROWS($1:61),"") | C73: =IF($B73="","",IF($E$7="Weekly",Start_Date+7*(ROWS($1:61)-1),EDATE(Start_Date,VLOOKUP(IF(ASTemp!$E$7="","Monthly",ASTemp!$E$7),Parameters!$B$3:$D$6,3,0)*(ROWS($1:61)-1)))) | D73: =IF($B73="","",YEAR(C73)) | E73: =IF($B73="","",VLOOKUP(MONTH(C73),Parameters!$F$2:$G$13,2,0)) | F73: =IF($B73="","",PV-N(J72)) | G73: =IF($B73="","",PMT(Rate,Nper,-PV,,Type)) | H73: =IF($B73="","",PPMT(Rate,ROWS($1:61),Nper,-PV,,Type)) | I73: =IF($B73="","",IPMT(Rate,ROWS($1:61),Nper,-PV,,Type)) | J73: =IF($B73="","",N(J72)+N(H73)) | K73: =IF($B73="","",N(K72)+N(I73)) | L73: =IF($B73="","",PV-J73) | M73: =IF($B73="","",J73/PV) | N73: =IF($B73="","",1-M73)
B74: =IF(ROWS($1:62)<=Nper,ROWS($1:62),"") | C74: =IF($B74="","",IF($E$7="Weekly",Start_Date+7*(ROWS($1:62)-1),EDATE(Start_Date,VLOOKUP(IF(ASTemp!$E$7="","Monthly",ASTemp!$E$7),Parameters!$B$3:$D$6,3,0)*(ROWS($1:62)-1)))) | D74: =IF($B74="","",YEAR(C74)) | E74: =IF($B74="","",VLOOKUP(MONTH(C74),Parameters!$F$2:$G$13,2,0)) | F74: =IF($B74="","",PV-N(J73)) | G74: =IF($B74="","",PMT(Rate,Nper,-PV,,Type)) | H74: =IF($B74="","",PPMT(Rate,ROWS($1:62),Nper,-PV,,Type)) | I74: =IF($B74="","",IPMT(Rate,ROWS($1:62),Nper,-PV,,Type)) | J74: =IF($B74="","",N(J73)+N(H74)) | K74: =IF($B74="","",N(K73)+N(I74)) | L74: =IF($B74="","",PV-J74) | M74: =IF($B74="","",J74/PV) | N74: =IF($B74="","",1-M74)
B75: =IF(ROWS($1:63)<=Nper,ROWS($1:63),"") | C75: =IF($B75="","",IF($E$7="Weekly",Start_Date+7*(ROWS($1:63)-1),EDATE(Start_Date,VLOOKUP(IF(ASTemp!$E$7="","Monthly",ASTemp!$E$7),Parameters!$B$3:$D$6,3,0)*(ROWS($1:63)-1)))) | D75: =IF($B75="","",YEAR(C75)) | E75: =IF($B75="","",VLOOKUP(MONTH(C75),Parameters!$F$2:$G$13,2,0)) | F75: =IF($B75="","",PV-N(J74)) | G75: =IF($B75="","",PMT(Rate,Nper,-PV,,Type)) | H75: =IF($B75="","",PPMT(Rate,ROWS($1:63),Nper,-PV,,Type)) | I75: =IF($B75="","",IPMT(Rate,ROWS($1:63),Nper,-PV,,Type)) | J75: =IF($B75="","",N(J74)+N(H75)) | K75: =IF($B75="","",N(K74)+N(I75)) | L75: =IF($B75="","",PV-J75) | M75: =IF($B75="","",J75/PV) | N75: =IF($B75="","",1-M75)
B76: =IF(ROWS($1:64)<=Nper,ROWS($1:64),"") | C76: =IF($B76="","",IF($E$7="Weekly",Start_Date+7*(ROWS($1:64)-1),EDATE(Start_Date,VLOOKUP(IF(ASTemp!$E$7="","Monthly",ASTemp!$E$7),Parameters!$B$3:$D$6,3,0)*(ROWS($1:64)-1)))) | D76: =IF($B76="","",YEAR(C76)) | E76: =IF($B76="","",VLOOKUP(MONTH(C76),Parameters!$F$2:$G$13,2,0)) | F76: =IF($B76="","",PV-N(J75)) | G76: =IF($B76="","",PMT(Rate,Nper,-PV,,Type)) | H76: =IF($B76="","",PPMT(Rate,ROWS($1:64),Nper,-PV,,Type)) | I76: =IF($B76="","",IPMT(Rate,ROWS($1:64),Nper,-PV,,Type)) | J76: =IF($B76="","",N(J75)+N(H76)) | K76: =IF($B76="","",N(K75)+N(I76)) | L76: =IF($B76="","",PV-J76) | M76: =IF($B76="","",J76/PV) | N76: =IF($B76="","",1-M76)
B77: =IF(ROWS($1:65)<=Nper,ROWS($1:65),"") | C77: =IF($B77="","",IF($E$7="Weekly",Start_Date+7*(ROWS($1:65)-1),EDATE(Start_Date,VLOOKUP(IF(ASTemp!$E$7="","Monthly",ASTemp!$E$7),Parameters!$B$3:$D$6,3,0)*(ROWS($1:65)-1)))) | D77: =IF($B77="","",YEAR(C77)) | E77: =IF($B77="","",VLOOKUP(MONTH(C77),Parameters!$F$2:$G$13,2,0)) | F77: =IF($B77="","",PV-N(J76)) | G77: =IF($B77="","",PMT(Rate,Nper,-PV,,Type)) | H77: =IF($B77="","",PPMT(Rate,ROWS($1:65),Nper,-PV,,Type)) | I77: =IF($B77="","",IPMT(Rate,ROWS($1:65),Nper,-PV,,Type)) | J77: =IF($B77="","",N(J76)+N(H77)) | K77: =IF($B77="","",N(K76)+N(I77)) | L77: =IF($B77="","",PV-J77) | M77: =IF($B77="","",J77/PV) | N77: =IF($B77="","",1-M77)
B78: =IF(ROWS($1:66)<=Nper,ROWS($1:66),"") | C78: =IF($B78="","",IF($E$7="Weekly",Start_Date+7*(ROWS($1:66)-1),EDATE(Start_Date,VLOOKUP(IF(ASTemp!$E$7="","Monthly",ASTemp!$E$7),Parameters!$B$3:$D$6,3,0)*(ROWS($1:66)-1)))) | D78: =IF($B78="","",YEAR(C78)) | E78: =IF($B78="","",VLOOKUP(MONTH(C78),Parameters!$F$2:$G$13,2,0)) | F78: =IF($B78="","",PV-N(J77)) | G78: =IF($B78="","",PMT(Rate,Nper,-PV,,Type)) | H78: =IF($B78="","",PPMT(Rate,ROWS($1:66),Nper,-PV,,Type)) | I78: =IF($B78="","",IPMT(Rate,ROWS($1:66),Nper,-PV,,Type)) | J78: =IF($B78="","",N(J77)+N(H78)) | K78: =IF($B78="","",N(K77)+N(I78)) | L78: =IF($B78="","",PV-J78) | M78: =IF($B78="","",J78/PV) | N78: =IF($B78="","",1-M78)
B79: =IF(ROWS($1:67)<=Nper,ROWS($1:67),"") | C79: =IF($B79="","",IF($E$7="Weekly",Start_Date+7*(ROWS($1:67)-1),EDATE(Start_Date,VLOOKUP(IF(ASTemp!$E$7="","Monthly",ASTemp!$E$7),Parameters!$B$3:$D$6,3,0)*(ROWS($1:67)-1)))) | D79: =IF($B79="","",YEAR(C79)) | E79: =IF($B79="","",VLOOKUP(MONTH(C79),Parameters!$F$2:$G$13,2,0)) | F79: =IF($B79="","",PV-N(J78)) | G79: =IF($B79="","",PMT(Rate,Nper,-PV,,Type)) | H79: =IF($B79="","",PPMT(Rate,ROWS($1:67),Nper,-PV,,Type)) | I79: =IF($B79="","",IPMT(Rate,ROWS($1:67),Nper,-PV,,Type)) | J79: =IF($B79="","",N(J78)+N(H79)) | K79: =IF($B79="","",N(K78)+N(I79)) | L79: =IF($B79="","",PV-J79) | M79: =IF($B79="","",J79/PV) | N79: =IF($B79="","",1-M79)
B80: =IF(ROWS($1:68)<=Nper,ROWS($1:68),"") | C80: =IF($B80="","",IF($E$7="Weekly",Start_Date+7*(ROWS($1:68)-1),EDATE(Start_Date,VLOOKUP(IF(ASTemp!$E$7="","Monthly",ASTemp!$E$7),Parameters!$B$3:$D$6,3,0)*(ROWS($1:68)-1)))) | D80: =IF($B80="","",YEAR(C80)) | E80: =IF($B80="","",VLOOKUP(MONTH(C80),Parameters!$F$2:$G$13,2,0)) | F80: =IF($B80="","",PV-N(J79)) | G80: =IF($B80="","",PMT(Rate,Nper,-PV,,Type)) | H80: =IF($B80="","",PPMT(Rate,ROWS($1:68),Nper,-PV,,Type)) | I80: =IF($B80="","",IPMT(Rate,ROWS($1:68),Nper,-PV,,Type)) | J80: =IF($B80="","",N(J79)+N(H80)) | K80: =IF($B80="","",N(K79)+N(I80)) | L80: =IF($B80="","",PV-J80) | M80: =IF($B80="","",J80/PV) | N80: =IF($B80="","",1-M80)
B81: =IF(ROWS($1:69)<=Nper,ROWS($1:69),"") | C81: =IF($B81="","",IF($E$7="Weekly",Start_Date+7*(ROWS($1:69)-1),EDATE(Start_Date,VLOOKUP(IF(ASTemp!$E$7="","Monthly",ASTemp!$E$7),Parameters!$B$3:$D$6,3,0)*(ROWS($1:69)-1)))) | D81: =IF($B81="","",YEAR(C81)) | E81: =IF($B81="","",VLOOKUP(MONTH(C81),Parameters!$F$2:$G$13,2,0)) | F81: =IF($B81="","",PV-N(J80)) | G81: =IF($B81="","",PMT(Rate,Nper,-PV,,Type)) | H81: =IF($B81="","",PPMT(Rate,ROWS($1:69),Nper,-PV,,Type)) | I81: =IF($B81="","",IPMT(Rate,ROWS($1:69),Nper,-PV,,Type)) | J81: =IF($B81="","",N(J80)+N(H81)) | K81: =IF($B81="","",N(K80)+N(I81)) | L81: =IF($B81="","",PV-J81) | M81: =IF($B81="","",J81/PV) | N81: =IF($B81="","",1-M81)
B82: =IF(ROWS($1:70)<=Nper,ROWS($1:70),"") | C82: =IF($B82="","",IF($E$7="Weekly",Start_Date+7*(ROWS($1:70)-1),EDATE(Start_Date,VLOOKUP(IF(ASTemp!$E$7="","Monthly",ASTemp!$E$7),Parameters!$B$3:$D$6,3,0)*(ROWS($1:70)-1)))) | D82: =IF($B82="","",YEAR(C82)) | E82: =IF($B82="","",VLOOKUP(MONTH(C82),Parameters!$F$2:$G$13,2,0)) | F82: =IF($B82="","",PV-N(J81)) | G82: =IF($B82="","",PMT(Rate,Nper,-PV,,Type)) | H82: =IF($B82="","",PPMT(Rate,ROWS($1:70),Nper,-PV,,Type)) | I82: =IF($B82="","",IPMT(Rate,ROWS($1:70),Nper,-PV,,Type)) | J82: =IF($B82="","",N(J81)+N(H82)) | K82: =IF($B82="","",N(K81)+N(I82)) | L82: =IF($B82="","",PV-J82) | M82: =IF($B82="","",J82/PV) | N82: =IF($B82="","",1-M82)
B83: =IF(ROWS($1:71)<=Nper,ROWS($1:71),"") | C83: =IF($B83="","",IF($E$7="Weekly",Start_Date+7*(ROWS($1:71)-1),EDATE(Start_Date,VLOOKUP(IF(ASTemp!$E$7="","Monthly",ASTemp!$E$7),Parameters!$B$3:$D$6,3,0)*(ROWS($1:71)-1)))) | D83: =IF($B83="","",YEAR(C83)) | E83: =IF($B83="","",VLOOKUP(MONTH(C83),Parameters!$F$2:$G$13,2,0)) | F83: =IF($B83="","",PV-N(J82)) | G83: =IF($B83="","",PMT(Rate,Nper,-PV,,Type)) | H83: =IF($B83="","",PPMT(Rate,ROWS($1:71),Nper,-PV,,Type)) | I83: =IF($B83="","",IPMT(Rate,ROWS($1:71),Nper,-PV,,Type)) | J83: =IF($B83="","",N(J82)+N(H83)) | K83: =IF($B83="","",N(K82)+N(I83)) | L83: =IF($B83="","",PV-J83) | M83: =IF($B83="","",J83/PV) | N83: =IF($B83="","",1-M83)
B84: =IF(ROWS($1:72)<=Nper,ROWS($1:72),"") | C84: =IF($B84="","",IF($E$7="Weekly",Start_Date+7*(ROWS($1:72)-1),EDATE(Start_Date,VLOOKUP(IF(ASTemp!$E$7="","Monthly",ASTemp!$E$7),Parameters!$B$3:$D$6,3,0)*(ROWS($1:72)-1)))) | D84: =IF($B84="","",YEAR(C84)) | E84: =IF($B84="","",VLOOKUP(MONTH(C84),Parameters!$F$2:$G$13,2,0)) | F84: =IF($B84="","",PV-N(J83)) | G84: =IF($B84="","",PMT(Rate,Nper,-PV,,Type)) | H84: =IF($B84="","",PPMT(Rate,ROWS($1:72),Nper,-PV,,Type)) | I84: =IF($B84="","",IPMT(Rate,ROWS($1:72),Nper,-PV,,Type)) | J84: =IF($B84="","",N(J83)+N(H84)) | K84: =IF($B84="","",N(K83)+N(I84)) | L84: =IF($B84="","",PV-J84) | M84: =IF($B84="","",J84/PV) | N84: =IF($B84="","",1-M84)
B85: =IF(ROWS($1:73)<=Nper,ROWS($1:73),"") | C85: =IF($B85="","",IF($E$7="Weekly",Start_Date+7*(ROWS($1:73)-1),EDATE(Start_Date,VLOOKUP(IF(ASTemp!$E$7="","Monthly",ASTemp!$E$7),Parameters!$B$3:$D$6,3,0)*(ROWS($1:73)-1)))) | D85: =IF($B85="","",YEAR(C85)) | E85: =IF($B85="","",VLOOKUP(MONTH(C85),Parameters!$F$2:$G$13,2,0)) | F85: =IF($B85="","",PV-N(J84)) | G85: =IF($B85="","",PMT(Rate,Nper,-PV,,Type)) | H85: =IF($B85="","",PPMT(Rate,ROWS($1:73),Nper,-PV,,Type)) | I85: =IF($B85="","",IPMT(Rate,ROWS($1:73),Nper,-PV,,Type)) | J85: =IF($B85="","",N(J84)+N(H85)) | K85: =IF($B85="","",N(K84)+N(I85)) | L85: =IF($B85="","",PV-J85) | M85: =IF($B85="","",J85/PV) | N85: =IF($B85="","",1-M85)
B86: =IF(ROWS($1:74)<=Nper,ROWS($1:74),"") | C86: =IF($B86="","",IF($E$7="Weekly",Start_Date+7*(ROWS($1:74)-1),EDATE(Start_Date,VLOOKUP(IF(ASTemp!$E$7="","Monthly",ASTemp!$E$7),Parameters!$B$3:$D$6,3,0)*(ROWS($1:74)-1)))) | D86: =IF($B86="","",YEAR(C86)) | E86: =IF($B86="","",VLOOKUP(MONTH(C86),Parameters!$F$2:$G$13,2,0)) | F86: =IF($B86="","",PV-N(J85)) | G86: =IF($B86="","",PMT(Rate,Nper,-PV,,Type)) | H86: =IF($B86="","",PPMT(Rate,ROWS($1:74),Nper,-PV,,Type)) | I86: =IF($B86="","",IPMT(Rate,ROWS($1:74),Nper,-PV,,Type)) | J86: =IF($B86="","",N(J85)+N(H86)) | K86: =IF($B86="","",N(K85)+N(I86)) | L86: =IF($B86="","",PV-J86) | M86: =IF($B86="","",J86/PV) | N86: =IF($B86="","",1-M86)
B87: =IF(ROWS($1:75)<=Nper,ROWS($1:75),"") | C87: =IF($B87="","",IF($E$7="Weekly",Start_Date+7*(ROWS($1:75)-1),EDATE(Start_Date,VLOOKUP(IF(ASTemp!$E$7="","Monthly",ASTemp!$E$7),Parameters!$B$3:$D$6,3,0)*(ROWS($1:75)-1)))) | D87: =IF($B87="","",YEAR(C87)) | E87: =IF($B87="","",VLOOKUP(MONTH(C87),Parameters!$F$2:$G$13,2,0)) | F87: =IF($B87="","",PV-N(J86)) | G87: =IF($B87="","",PMT(Rate,Nper,-PV,,Type)) | H87: =IF($B87="","",PPMT(Rate,ROWS($1:75),Nper,-PV,,Type)) | I87: =IF($B87="","",IPMT(Rate,ROWS($1:75),Nper,-PV,,Type)) | J87: =IF($B87="","",N(J86)+N(H87)) | K87: =IF($B87="","",N(K86)+N(I87)) | L87: =IF($B87="","",PV-J87) | M87: =IF($B87="","",J87/PV) | N87: =IF($B87="","",1-M87)
B88: =IF(ROWS($1:76)<=Nper,ROWS($1:76),"") | C88: =IF($B88="","",IF($E$7="Weekly",Start_Date+7*(ROWS($1:76)-1),EDATE(Start_Date,VLOOKUP(IF(ASTemp!$E$7="","Monthly",ASTemp!$E$7),Parameters!$B$3:$D$6,3,0)*(ROWS($1:76)-1)))) | D88: =IF($B88="","",YEAR(C88)) | E88: =IF($B88="","",VLOOKUP(MONTH(C88),Parameters!$F$2:$G$13,2,0)) | F88: =IF($B88="","",PV-N(J87)) | G88: =IF($B88="","",PMT(Rate,Nper,-PV,,Type)) | H88: =IF($B88="","",PPMT(Rate,ROWS($1:76),Nper,-PV,,Type)) | I88: =IF($B88="","",IPMT(Rate,ROWS($1:76),Nper,-PV,,Type)) | J88: =IF($B88="","",N(J87)+N(H88)) | K88: =IF($B88="","",N(K87)+N(I88)) | L88: =IF($B88="","",PV-J88) | M88: =IF($B88="","",J88/PV) | N88: =IF($B88="","",1-M88)
B89: =IF(ROWS($1:77)<=Nper,ROWS($1:77),"") | C89: =IF($B89="","",IF($E$7="Weekly",Start_Date+7*(ROWS($1:77)-1),EDATE(Start_Date,VLOOKUP(IF(ASTemp!$E$7="","Monthly",ASTemp!$E$7),Parameters!$B$3:$D$6,3,0)*(ROWS($1:77)-1)))) | D89: =IF($B89="","",YEAR(C89)) | E89: =IF($B89="","",VLOOKUP(MONTH(C89),Parameters!$F$2:$G$13,2,0)) | F89: =IF($B89="","",PV-N(J88)) | G89: =IF($B89="","",PMT(Rate,Nper,-PV,,Type)) | H89: =IF($B89="","",PPMT(Rate,ROWS($1:77),Nper,-PV,,Type)) | I89: =IF($B89="","",IPMT(Rate,ROWS($1:77),Nper,-PV,,Type)) | J89: =IF($B89="","",N(J88)+N(H89)) | K89: =IF($B89="","",N(K88)+N(I89)) | L89: =IF($B89="","",PV-J89) | M89: =IF($B89="","",J89/PV) | N89: =IF($B89="","",1-M89)
B90: =IF(ROWS($1:78)<=Nper,ROWS($1:78),"") | C90: =IF($B90="","",IF($E$7="Weekly",Start_Date+7*(ROWS($1:78)-1),EDATE(Start_Date,VLOOKUP(IF(ASTemp!$E$7="","Monthly",ASTemp!$E$7),Parameters!$B$3:$D$6,3,0)*(ROWS($1:78)-1)))) | D90: =IF($B90="","",YEAR(C90)) | E90: =IF($B90="","",VLOOKUP(MONTH(C90),Parameters!$F$2:$G$13,2,0)) | F90: =IF($B90="","",PV-N(J89)) | G90: =IF($B90="","",PMT(Rate,Nper,-PV,,Type)) | H90: =IF($B90="","",PPMT(Rate,ROWS($1:78),Nper,-PV,,Type)) | I90: =IF($B90="","",IPMT(Rate,ROWS($1:78),Nper,-PV,,Type)) | J90: =IF($B90="","",N(J89)+N(H90)) | K90: =IF($B90="","",N(K89)+N(I90)) | L90: =IF($B90="","",PV-J90) | M90: =IF($B90="","",J90/PV) | N90: =IF($B90="","",1-M90)
B91: =IF(ROWS($1:79)<=Nper,ROWS($1:79),"") | C91: =IF($B91="","",IF($E$7="Weekly",Start_Date+7*(ROWS($1:79)-1),EDATE(Start_Date,VLOOKUP(IF(ASTemp!$E$7="","Monthly",ASTemp!$E$7),Parameters!$B$3:$D$6,3,0)*(ROWS($1:79)-1)))) | D91: =IF($B91="","",YEAR(C91)) | E91: =IF($B91="","",VLOOKUP(MONTH(C91),Parameters!$F$2:$G$13,2,0)) | F91: =IF($B91="","",PV-N(J90)) | G91: =IF($B91="","",PMT(Rate,Nper,-PV,,Type)) | H91: =IF($B91="","",PPMT(Rate,ROWS($1:79),Nper,-PV,,Type)) | I91: =IF($B91="","",IPMT(Rate,ROWS($1:79),Nper,-PV,,Type)) | J91: =IF($B91="","",N(J90)+N(H91)) | K91: =IF($B91="","",N(K90)+N(I91)) | L91: =IF($B91="","",PV-J91) | M91: =IF($B91="","",J91/PV) | N91: =IF($B91="","",1-M91)
B92: =IF(ROWS($1:80)<=Nper,ROWS($1:80),"") | C92: =IF($B92="","",IF($E$7="Weekly",Start_Date+7*(ROWS($1:80)-1),EDATE(Start_Date,VLOOKUP(IF(ASTemp!$E$7="","Monthly",ASTemp!$E$7),Parameters!$B$3:$D$6,3,0)*(ROWS($1:80)-1)))) | D92: =IF($B92="","",YEAR(C92)) | E92: =IF($B92="","",VLOOKUP(MONTH(C92),Parameters!$F$2:$G$13,2,0)) | F92: =IF($B92="","",PV-N(J91)) | G92: =IF($B92="","",PMT(Rate,Nper,-PV,,Type)) | H92: =IF($B92="","",PPMT(Rate,ROWS($1:80),Nper,-PV,,Type)) | I92: =IF($B92="","",IPMT(Rate,ROWS($1:80),Nper,-PV,,Type)) | J92: =IF($B92="","",N(J91)+N(H92)) | K92: =IF($B92="","",N(K91)+N(I92)) | L92: =IF($B92="","",PV-J92) | M92: =IF($B92="","",J92/PV) | N92: =IF($B92="","",1-M92)
B93: =IF(ROWS($1:81)<=Nper,ROWS($1:81),"") | C93: =IF($B93="","",IF($E$7="Weekly",Start_Date+7*(ROWS($1:81)-1),EDATE(Start_Date,VLOOKUP(IF(ASTemp!$E$7="","Monthly",ASTemp!$E$7),Parameters!$B$3:$D$6,3,0)*(ROWS($1:81)-1)))) | D93: =IF($B93="","",YEAR(C93)) | E93: =IF($B93="","",VLOOKUP(MONTH(C93),Parameters!$F$2:$G$13,2,0)) | F93: =IF($B93="","",PV-N(J92)) | G93: =IF($B93="","",PMT(Rate,Nper,-PV,,Type)) | H93: =IF($B93="","",PPMT(Rate,ROWS($1:81),Nper,-PV,,Type)) | I93: =IF($B93="","",IPMT(Rate,ROWS($1:81),Nper,-PV,,Type)) | J93: =IF($B93="","",N(J92)+N(H93)) | K93: =IF($B93="","",N(K92)+N(I93)) | L93: =IF($B93="","",PV-J93) | M93: =IF($B93="","",J93/PV) | N93: =IF($B93="","",1-M93)
B94: =IF(ROWS($1:82)<=Nper,ROWS($1:82),"") | C94: =IF($B94="","",IF($E$7="Weekly",Start_Date+7*(ROWS($1:82)-1),EDATE(Start_Date,VLOOKUP(IF(ASTemp!$E$7="","Monthly",ASTemp!$E$7),Parameters!$B$3:$D$6,3,0)*(ROWS($1:82)-1)))) | D94: =IF($B94="","",YEAR(C94)) | E94: =IF($B94="","",VLOOKUP(MONTH(C94),Parameters!$F$2:$G$13,2,0)) | F94: =IF($B94="","",PV-N(J93)) | G94: =IF($B94="","",PMT(Rate,Nper,-PV,,Type)) | H94: =IF($B94="","",PPMT(Rate,ROWS($1:82),Nper,-PV,,Type)) | I94: =IF($B94="","",IPMT(Rate,ROWS($1:82),Nper,-PV,,Type)) | J94: =IF($B94="","",N(J93)+N(H94)) | K94: =IF($B94="","",N(K93)+N(I94)) | L94: =IF($B94="","",PV-J94) | M94: =IF($B94="","",J94/PV) | N94: =IF($B94="","",1-M94)
B95: =IF(ROWS($1:83)<=Nper,ROWS($1:83),"") | C95: =IF($B95="","",IF($E$7="Weekly",Start_Date+7*(ROWS($1:83)-1),EDATE(Start_Date,VLOOKUP(IF(ASTemp!$E$7="","Monthly",ASTemp!$E$7),Parameters!$B$3:$D$6,3,0)*(ROWS($1:83)-1)))) | D95: =IF($B95="","",YEAR(C95)) | E95: =IF($B95="","",VLOOKUP(MONTH(C95),Parameters!$F$2:$G$13,2,0)) | F95: =IF($B95="","",PV-N(J94)) | G95: =IF($B95="","",PMT(Rate,Nper,-PV,,Type)) | H95: =IF($B95="","",PPMT(Rate,ROWS($1:83),Nper,-PV,,Type)) | I95: =IF($B95="","",IPMT(Rate,ROWS($1:83),Nper,-PV,,Type)) | J95: =IF($B95="","",N(J94)+N(H95)) | K95: =IF($B95="","",N(K94)+N(I95)) | L95: =IF($B95="","",PV-J95) | M95: =IF($B95="","",J95/PV) | N95: =IF($B95="","",1-M95)
B96: =IF(ROWS($1:84)<=Nper,ROWS($1:84),"") | C96: =IF($B96="","",IF($E$7="Weekly",Start_Date+7*(ROWS($1:84)-1),EDATE(Start_Date,VLOOKUP(IF(ASTemp!$E$7="","Monthly",ASTemp!$E$7),Parameters!$B$3:$D$6,3,0)*(ROWS($1:84)-1)))) | D96: =IF($B96="","",YEAR(C96)) | E96: =IF($B96="","",VLOOKUP(MONTH(C96),Parameters!$F$2:$G$13,2,0)) | F96: =IF($B96="","",PV-N(J95)) | G96: =IF($B96="","",PMT(Rate,Nper,-PV,,Type)) | H96: =IF($B96="","",PPMT(Rate,ROWS($1:84),Nper,-PV,,Type)) | I96: =IF($B96="","",IPMT(Rate,ROWS($1:84),Nper,-PV,,Type)) | J96: =IF($B96="","",N(J95)+N(H96)) | K96: =IF($B96="","",N(K95)+N(I96)) | L96: =IF($B96="","",PV-J96) | M96: =IF($B96="","",J96/PV) | N96: =IF($B96="","",1-M96)
B97: =IF(ROWS($1:85)<=Nper,ROWS($1:85),"") | C97: =IF($B97="","",IF($E$7="Weekly",Start_Date+7*(ROWS($1:85)-1),EDATE(Start_Date,VLOOKUP(IF(ASTemp!$E$7="","Monthly",ASTemp!$E$7),Parameters!$B$3:$D$6,3,0)*(ROWS($1:85)-1)))) | D97: =IF($B97="","",YEAR(C97)) | E97: =IF($B97="","",VLOOKUP(MONTH(C97),Parameters!$F$2:$G$13,2,0)) | F97: =IF($B97="","",PV-N(J96)) | G97: =IF($B97="","",PMT(Rate,Nper,-PV,,Type)) | H97: =IF($B97="","",PPMT(Rate,ROWS($1:85),Nper,-PV,,Type)) | I97: =IF($B97="","",IPMT(Rate,ROWS($1:85),Nper,-PV,,Type)) | J97: =IF($B97="","",N(J96)+N(H97)) | K97: =IF($B97="","",N(K96)+N(I97)) | L97: =IF($B97="","",PV-J97) | M97: =IF($B97="","",J97/PV) | N97: =IF($B97="","",1-M97)
B98: =IF(ROWS($1:86)<=Nper,ROWS($1:86),"") | C98: =IF($B98="","",IF($E$7="Weekly",Start_Date+7*(ROWS($1:86)-1),EDATE(Start_Date,VLOOKUP(IF(ASTemp!$E$7="","Monthly",ASTemp!$E$7),Parameters!$B$3:$D$6,3,0)*(ROWS($1:86)-1)))) | D98: =IF($B98="","",YEAR(C98)) | E98: =IF($B98="","",VLOOKUP(MONTH(C98),Parameters!$F$2:$G$13,2,0)) | F98: =IF($B98="","",PV-N(J97)) | G98: =IF($B98="","",PMT(Rate,Nper,-PV,,Type)) | H98: =IF($B98="","",PPMT(Rate,ROWS($1:86),Nper,-PV,,Type)) | I98: =IF($B98="","",IPMT(Rate,ROWS($1:86),Nper,-PV,,Type)) | J98: =IF($B98="","",N(J97)+N(H98)) | K98: =IF($B98="","",N(K97)+N(I98)) | L98: =IF($B98="","",PV-J98) | M98: =IF($B98="","",J98/PV) | N98: =IF($B98="","",1-M98)
B99: =IF(ROWS($1:87)<=Nper,ROWS($1:87),"") | C99: =IF($B99="","",IF($E$7="Weekly",Start_Date+7*(ROWS($1:87)-1),EDATE(Start_Date,VLOOKUP(IF(ASTemp!$E$7="","Monthly",ASTemp!$E$7),Parameters!$B$3:$D$6,3,0)*(ROWS($1:87)-1)))) | D99: =IF($B99="","",YEAR(C99)) | E99: =IF($B99="","",VLOOKUP(MONTH(C99),Parameters!$F$2:$G$13,2,0)) | F99: =IF($B99="","",PV-N(J98)) | G99: =IF($B99="","",PMT(Rate,Nper,-PV,,Type)) | H99: =IF($B99="","",PPMT(Rate,ROWS($1:87),Nper,-PV,,Type)) | I99: =IF($B99="","",IPMT(Rate,ROWS($1:87),Nper,-PV,,Type)) | J99: =IF($B99="","",N(J98)+N(H99)) | K99: =IF($B99="","",N(K98)+N(I99)) | L99: =IF($B99="","",PV-J99) | M99: =IF($B99="","",J99/PV) | N99: =IF($B99="","",1-M99)
B100: =IF(ROWS($1:88)<=Nper,ROWS($1:88),"") | C100: =IF($B100="","",IF($E$7="Weekly",Start_Date+7*(ROWS($1:88)-1),EDATE(Start_Date,VLOOKUP(IF(ASTemp!$E$7="","Monthly",ASTemp!$E$7),Parameters!$B$3:$D$6,3,0)*(ROWS($1:88)-1)))) | D100: =IF($B100="","",YEAR(C100)) | E100: =IF($B100="","",VLOOKUP(MONTH(C100),Parameters!$F$2:$G$13,2,0)) | F100: =IF($B100="","",PV-N(J99)) | G100: =IF($B100="","",PMT(Rate,Nper,-PV,,Type)) | H100: =IF($B100="","",PPMT(Rate,ROWS($1:88),Nper,-PV,,Type)) | I100: =IF($B100="","",IPMT(Rate,ROWS($1:88),Nper,-PV,,Type)) | J100: =IF($B100="","",N(J99)+N(H100)) | K100: =IF($B100="","",N(K99)+N(I100)) | L100: =IF($B100="","",PV-J100) | M100: =IF($B100="","",J100/PV) | N100: =IF($B100="","",1-M100)
B101: =IF(ROWS($1:89)<=Nper,ROWS($1:89),"") | C101: =IF($B101="","",IF($E$7="Weekly",Start_Date+7*(ROWS($1:89)-1),EDATE(Start_Date,VLOOKUP(IF(ASTemp!$E$7="","Monthly",ASTemp!$E$7),Parameters!$B$3:$D$6,3,0)*(ROWS($1:89)-1)))) | D101: =IF($B101="","",YEAR(C101)) | E101: =IF($B101="","",VLOOKUP(MONTH(C101),Parameters!$F$2:$G$13,2,0)) | F101: =IF($B101="","",PV-N(J100)) | G101: =IF($B101="","",PMT(Rate,Nper,-PV,,Type)) | H101: =IF($B101="","",PPMT(Rate,ROWS($1:89),Nper,-PV,,Type)) | I101: =IF($B101="","",IPMT(Rate,ROWS($1:89),Nper,-PV,,Type)) | J101: =IF($B101="","",N(J100)+N(H101)) | K101: =IF($B101="","",N(K100)+N(I101)) | L101: =IF($B101="","",PV-J101) | M101: =IF($B101="","",J101/PV) | N101: =IF($B101="","",1-M101)
B102: =IF(ROWS($1:90)<=Nper,ROWS($1:90),"") | C102: =IF($B102="","",IF($E$7="Weekly",Start_Date+7*(ROWS($1:90)-1),EDATE(Start_Date,VLOOKUP(IF(ASTemp!$E$7="","Monthly",ASTemp!$E$7),Parameters!$B$3:$D$6,3,0)*(ROWS($1:90)-1)))) | D102: =IF($B102="","",YEAR(C102)) | E102: =IF($B102="","",VLOOKUP(MONTH(C102),Parameters!$F$2:$G$13,2,0)) | F102: =IF($B102="","",PV-N(J101)) | G102: =IF($B102="","",PMT(Rate,Nper,-PV,,Type)) | H102: =IF($B102="","",PPMT(Rate,ROWS($1:90),Nper,-PV,,Type)) | I102: =IF($B102="","",IPMT(Rate,ROWS($1:90),Nper,-PV,,Type)) | J102: =IF($B102="","",N(J101)+N(H102)) | K102: =IF($B102="","",N(K101)+N(I102)) | L102: =IF($B102="","",PV-J102) | M102: =IF($B102="","",J102/PV) | N102: =IF($B102="","",1-M102)
...

Sheet Parameters
A2: Weeks | B2: Weekly | C2: 52 | F2: 1 | G2: Jan | H2: 1 | J2: Start / End | K2: 2
A3: Months | B3: Monthly | C3: 12 | D3: 1 | F3: 2 | G3: Feb | H3: 2 | J3: Rate | K3: =(ASTemp!$E$5*VLOOKUP(IF(ASTemp!$F$5="","Yearly",ASTemp!$F$5),Parameters!$B$2:$C$6,2,0))/VLOOKUP(IF(ASTemp!$E$7="","Monthly",ASTemp!$E$7),$B$2:$C$6,2,0) -> 0.00096153846
A4: Quarters | B4: Quarterly | C4: 4 | D4: 3 | F4: 3 | G4: Mar | H4: 3 | J4: Nper | K4: =ASTemp!$E$6*VLOOKUP(IF(ASTemp!$E$7="","Monthly",ASTemp!$E$7),$B$2:$C$6,2,0)/VLOOKUP(IF(ASTemp!$F$6="","Years",ASTemp!$F$6),Parameters!$A$2:$C$6,3,0) -> 52
A5: Half Years | B5: Six Monthly | C5: 2 | D5: 6 | F5: 4 | G5: Apr | H5: 4 | J5: Type | K5: =IF($K$2=1,1,0) -> 0
A6: Years | B6: Yearly | C6: 1 | D6: 12 | F6: 5 | G6: May | H6: 5 | J6: Start Date | K6: =IF(K5=0,EOMONTH(DATE(IF(ASTemp!$E$8="",YEAR(TODAY()),ASTemp!$E$8),IF(ASTemp!$F$8="",MONTH(TODAY()),VLOOKUP(ASTemp!$F$8,$G$2:$GT$13,2,0)),1),0),DATE(IF(ASTemp!$E$8="",YEAR(TODAY()),ASTemp!$E$8),IF(ASTemp!$F$8="",MONTH(TODAY()),VLOOKUP(ASTemp!$F$8,$G$2:$GT$13,2,0)),1)) -> 42277
F7: 6 | G7: Jun | H7: 6 | J7: Decimal Formatting | K7: =CHOOSE(ASTemp!$E$9+1,"0","0.0","0.00") -> 0.0
F8: 7 | G8: Jul | H8: 7 | J8: % Formatting | K8: =CHOOSE(ASTemp!$E$9+1,"0%","0.0%","0.00%") -> 0.0%
F9: 8 | G9: Aug | H9: 8
F10: 9 | G10: Sep | H10: 9
F11: 10 | G11: Oct | H11: 10
F12: 11 | G12: Nov | H12: 11
F13: 12 | G13: Dec | H13: 12
